<instance format="XCSP3" type="COP">
  <variables>
    <array id="x" size="[1138]"> 1..1138 </array>
  </variables>
  <constraints>
    <allDifferent> x[] </allDifferent>
  </constraints>
  <objectives>
    <minimize type="maximum"> min(dist(x[487],x[296]),sub(1138,dist(x[487],x[296]))) min(dist(x[487],x[279]),sub(1138,dist(x[487],x[279]))) min(dist(x[212],x[324]),sub(1138,dist(x[212],x[324]))) min(dist(x[212],x[279]),sub(1138,dist(x[212],x[279]))) min(dist(x[269],x[697]),sub(1138,dist(x[269],x[697]))) min(dist(x[269],x[685]),sub(1138,dist(x[269],x[685]))) min(dist(x[269],x[297]),sub(1138,dist(x[269],x[297]))) min(dist(x[269],x[667]),sub(1138,dist(x[269],x[667]))) min(dist(x[269],x[475]),sub(1138,dist(x[269],x[475]))) min(dist(x[996],x[718]),sub(1138,dist(x[996],x[718]))) min(dist(x[996],x[366]),sub(1138,dist(x[996],x[366]))) min(dist(x[996],x[950]),sub(1138,dist(x[996],x[950]))) min(dist(x[996],x[1073]),sub(1138,dist(x[996],x[1073]))) min(dist(x[996],x[1109]),sub(1138,dist(x[996],x[1109]))) min(dist(x[296],x[568]),sub(1138,dist(x[296],x[568]))) min(dist(x[1014],x[718]),sub(1138,dist(x[1014],x[718]))) min(dist(x[1014],x[736]),sub(1138,dist(x[1014],x[736]))) min(dist(x[1014],x[266]),sub(1138,dist(x[1014],x[266]))) min(dist(x[1014],x[1109]),sub(1138,dist(x[1014],x[1109]))) min(dist(x[718],x[736]),sub(1138,dist(x[718],x[736]))) min(dist(x[718],x[950]),sub(1138,dist(x[718],x[950]))) min(dist(x[718],x[1073]),sub(1138,dist(x[718],x[1073]))) min(dist(x[718],x[1109]),sub(1138,dist(x[718],x[1109]))) min(dist(x[326],x[555]),sub(1138,dist(x[326],x[555]))) min(dist(x[326],x[297]),sub(1138,dist(x[326],x[297]))) min(dist(x[326],x[464]),sub(1138,dist(x[326],x[464]))) min(dist(x[568],x[324]),sub(1138,dist(x[568],x[324]))) min(dist(x[568],x[667]),sub(1138,dist(x[568],x[667]))) min(dist(x[324],x[667]),sub(1138,dist(x[324],x[667]))) min(dist(x[697],x[719]),sub(1138,dist(x[697],x[719]))) min(dist(x[697],x[62]),sub(1138,dist(x[697],x[62]))) min(dist(x[697],x[419]),sub(1138,dist(x[697],x[419]))) min(dist(x[140],x[685]),sub(1138,dist(x[140],x[685]))) min(dist(x[140],x[667]),sub(1138,dist(x[140],x[667]))) min(dist(x[7],x[637]),sub(1138,dist(x[7],x[637]))) min(dist(x[377],x[63]),sub(1138,dist(x[377],x[63]))) min(dist(x[377],x[90]),sub(1138,dist(x[377],x[90]))) min(dist(x[377],x[727]),sub(1138,dist(x[377],x[727]))) min(dist(x[377],x[87]),sub(1138,dist(x[377],x[87]))) min(dist(x[377],x[871]),sub(1138,dist(x[377],x[871]))) min(dist(x[1038],x[144]),sub(1138,dist(x[1038],x[144]))) min(dist(x[1038],x[736]),sub(1138,dist(x[1038],x[736]))) min(dist(x[1038],x[1073]),sub(1138,dist(x[1038],x[1073]))) min(dist(x[144],x[680]),sub(1138,dist(x[144],x[680]))) min(dist(x[144],x[774]),sub(1138,dist(x[144],x[774]))) min(dist(x[144],x[4]),sub(1138,dist(x[144],x[4]))) min(dist(x[144],x[961]),sub(1138,dist(x[144],x[961]))) min(dist(x[555],x[297]),sub(1138,dist(x[555],x[297]))) min(dist(x[366],x[216]),sub(1138,dist(x[366],x[216]))) min(dist(x[366],x[534]),sub(1138,dist(x[366],x[534]))) min(dist(x[366],x[567]),sub(1138,dist(x[366],x[567]))) min(dist(x[366],x[950]),sub(1138,dist(x[366],x[950]))) min(dist(x[802],x[921]),sub(1138,dist(x[802],x[921]))) min(dist(x[802],x[345]),sub(1138,dist(x[802],x[345]))) min(dist(x[921],x[345]),sub(1138,dist(x[921],x[345]))) min(dist(x[628],x[345]),sub(1138,dist(x[628],x[345]))) min(dist(x[685],x[667]),sub(1138,dist(x[685],x[667]))) min(dist(x[685],x[670]),sub(1138,dist(x[685],x[670]))) min(dist(x[297],x[667]),sub(1138,dist(x[297],x[667]))) min(dist(x[297],x[15]),sub(1138,dist(x[297],x[15]))) min(dist(x[651],x[277]),sub(1138,dist(x[651],x[277]))) min(dist(x[736],x[1073]),sub(1138,dist(x[736],x[1073]))) min(dist(x[62],x[192]),sub(1138,dist(x[62],x[192]))) min(dist(x[62],x[266]),sub(1138,dist(x[62],x[266]))) min(dist(x[62],x[79]),sub(1138,dist(x[62],x[79]))) min(dist(x[192],x[837]),sub(1138,dist(x[192],x[837]))) min(dist(x[889],x[519]),sub(1138,dist(x[889],x[519]))) min(dist(x[889],x[248]),sub(1138,dist(x[889],x[248]))) min(dist(x[889],x[808]),sub(1138,dist(x[889],x[808]))) min(dist(x[519],x[168]),sub(1138,dist(x[519],x[168]))) min(dist(x[519],x[701]),sub(1138,dist(x[519],x[701]))) min(dist(x[248],x[488]),sub(1138,dist(x[248],x[488]))) min(dist(x[701],x[970]),sub(1138,dist(x[701],x[970]))) min(dist(x[808],x[887]),sub(1138,dist(x[808],x[887]))) min(dist(x[448],x[417]),sub(1138,dist(x[448],x[417]))) min(dist(x[31],x[417]),sub(1138,dist(x[31],x[417]))) min(dist(x[417],x[234]),sub(1138,dist(x[417],x[234]))) min(dist(x[417],x[478]),sub(1138,dist(x[417],x[478]))) min(dist(x[887],x[52]),sub(1138,dist(x[887],x[52]))) min(dist(x[887],x[109]),sub(1138,dist(x[887],x[109]))) min(dist(x[52],x[897]),sub(1138,dist(x[52],x[897]))) min(dist(x[52],x[969]),sub(1138,dist(x[52],x[969]))) min(dist(x[969],x[700]),sub(1138,dist(x[969],x[700]))) min(dist(x[109],x[234]),sub(1138,dist(x[109],x[234]))) min(dist(x[109],x[585]),sub(1138,dist(x[109],x[585]))) min(dist(x[234],x[746]),sub(1138,dist(x[234],x[746]))) min(dist(x[234],x[53]),sub(1138,dist(x[234],x[53]))) min(dist(x[234],x[677]),sub(1138,dist(x[234],x[677]))) min(dist(x[1116],x[590]),sub(1138,dist(x[1116],x[590]))) min(dist(x[979],x[592]),sub(1138,dist(x[979],x[592]))) min(dist(x[382],x[184]),sub(1138,dist(x[382],x[184]))) min(dist(x[905],x[147]),sub(1138,dist(x[905],x[147]))) min(dist(x[724],x[934]),sub(1138,dist(x[724],x[934]))) min(dist(x[470],x[956]),sub(1138,dist(x[470],x[956]))) min(dist(x[84],x[856]),sub(1138,dist(x[84],x[856]))) min(dist(x[590],x[227]),sub(1138,dist(x[590],x[227]))) min(dist(x[590],x[13]),sub(1138,dist(x[590],x[13]))) min(dist(x[227],x[204]),sub(1138,dist(x[227],x[204]))) min(dist(x[227],x[472]),sub(1138,dist(x[227],x[472]))) min(dist(x[227],x[220]),sub(1138,dist(x[227],x[220]))) min(dist(x[13],x[331]),sub(1138,dist(x[13],x[331]))) min(dist(x[592],x[147]),sub(1138,dist(x[592],x[147]))) min(dist(x[592],x[934]),sub(1138,dist(x[592],x[934]))) min(dist(x[592],x[115]),sub(1138,dist(x[592],x[115]))) min(dist(x[592],x[547]),sub(1138,dist(x[592],x[547]))) min(dist(x[592],x[220]),sub(1138,dist(x[592],x[220]))) min(dist(x[147],x[934]),sub(1138,dist(x[147],x[934]))) min(dist(x[147],x[274]),sub(1138,dist(x[147],x[274]))) min(dist(x[934],x[115]),sub(1138,dist(x[934],x[115]))) min(dist(x[934],x[524]),sub(1138,dist(x[934],x[524]))) min(dist(x[934],x[23]),sub(1138,dist(x[934],x[23]))) min(dist(x[274],x[184]),sub(1138,dist(x[274],x[184]))) min(dist(x[184],x[635]),sub(1138,dist(x[184],x[635]))) min(dist(x[184],x[874]),sub(1138,dist(x[184],x[874]))) min(dist(x[184],x[255]),sub(1138,dist(x[184],x[255]))) min(dist(x[184],x[17]),sub(1138,dist(x[184],x[17]))) min(dist(x[184],x[761]),sub(1138,dist(x[184],x[761]))) min(dist(x[204],x[1056]),sub(1138,dist(x[204],x[1056]))) min(dist(x[1056],x[1019]),sub(1138,dist(x[1056],x[1019]))) min(dist(x[1056],x[623]),sub(1138,dist(x[1056],x[623]))) min(dist(x[115],x[380]),sub(1138,dist(x[115],x[380]))) min(dist(x[115],x[219]),sub(1138,dist(x[115],x[219]))) min(dist(x[115],x[674]),sub(1138,dist(x[115],x[674]))) min(dist(x[115],x[684]),sub(1138,dist(x[115],x[684]))) min(dist(x[115],x[118]),sub(1138,dist(x[115],x[118]))) min(dist(x[380],x[767]),sub(1138,dist(x[380],x[767]))) min(dist(x[380],x[1078]),sub(1138,dist(x[380],x[1078]))) min(dist(x[380],x[888]),sub(1138,dist(x[380],x[888]))) min(dist(x[219],x[974]),sub(1138,dist(x[219],x[974]))) min(dist(x[219],x[674]),sub(1138,dist(x[219],x[674]))) min(dist(x[219],x[112]),sub(1138,dist(x[219],x[112]))) min(dist(x[974],x[850]),sub(1138,dist(x[974],x[850]))) min(dist(x[674],x[533]),sub(1138,dist(x[674],x[533]))) min(dist(x[674],x[142]),sub(1138,dist(x[674],x[142]))) min(dist(x[533],x[679]),sub(1138,dist(x[533],x[679]))) min(dist(x[533],x[262]),sub(1138,dist(x[533],x[262]))) min(dist(x[533],x[881]),sub(1138,dist(x[533],x[881]))) min(dist(x[684],x[483]),sub(1138,dist(x[684],x[483]))) min(dist(x[684],x[677]),sub(1138,dist(x[684],x[677]))) min(dist(x[684],x[142]),sub(1138,dist(x[684],x[142]))) min(dist(x[483],x[1071]),sub(1138,dist(x[483],x[1071]))) min(dist(x[483],x[436]),sub(1138,dist(x[483],x[436]))) min(dist(x[483],x[840]),sub(1138,dist(x[483],x[840]))) min(dist(x[188],x[1113]),sub(1138,dist(x[188],x[1113]))) min(dist(x[834],x[1113]),sub(1138,dist(x[834],x[1113]))) min(dist(x[257],x[56]),sub(1138,dist(x[257],x[56]))) min(dist(x[281],x[715]),sub(1138,dist(x[281],x[715]))) min(dist(x[281],x[445]),sub(1138,dist(x[281],x[445]))) min(dist(x[550],x[715]),sub(1138,dist(x[550],x[715]))) min(dist(x[550],x[895]),sub(1138,dist(x[550],x[895]))) min(dist(x[550],x[1047]),sub(1138,dist(x[550],x[1047]))) min(dist(x[550],x[554]),sub(1138,dist(x[550],x[554]))) min(dist(x[550],x[492]),sub(1138,dist(x[550],x[492]))) min(dist(x[550],x[300]),sub(1138,dist(x[550],x[300]))) min(dist(x[550],x[794]),sub(1138,dist(x[550],x[794]))) min(dist(x[550],x[122]),sub(1138,dist(x[550],x[122]))) min(dist(x[550],x[653]),sub(1138,dist(x[550],x[653]))) min(dist(x[550],x[687]),sub(1138,dist(x[550],x[687]))) min(dist(x[550],x[194]),sub(1138,dist(x[550],x[194]))) min(dist(x[550],x[459]),sub(1138,dist(x[550],x[459]))) min(dist(x[715],x[821]),sub(1138,dist(x[715],x[821]))) min(dist(x[557],x[991]),sub(1138,dist(x[557],x[991]))) min(dist(x[557],x[275]),sub(1138,dist(x[557],x[275]))) min(dist(x[524],x[773]),sub(1138,dist(x[524],x[773]))) min(dist(x[773],x[771]),sub(1138,dist(x[773],x[771]))) min(dist(x[773],x[571]),sub(1138,dist(x[773],x[571]))) min(dist(x[773],x[275]),sub(1138,dist(x[773],x[275]))) min(dist(x[773],x[578]),sub(1138,dist(x[773],x[578]))) min(dist(x[771],x[1114]),sub(1138,dist(x[771],x[1114]))) min(dist(x[1114],x[1113]),sub(1138,dist(x[1114],x[1113]))) min(dist(x[1114],x[481]),sub(1138,dist(x[1114],x[481]))) min(dist(x[1114],x[74]),sub(1138,dist(x[1114],x[74]))) min(dist(x[1114],x[1015]),sub(1138,dist(x[1114],x[1015]))) min(dist(x[1114],x[154]),sub(1138,dist(x[1114],x[154]))) min(dist(x[1114],x[682]),sub(1138,dist(x[1114],x[682]))) min(dist(x[1114],x[653]),sub(1138,dist(x[1114],x[653]))) min(dist(x[1114],x[687]),sub(1138,dist(x[1114],x[687]))) min(dist(x[1114],x[1004]),sub(1138,dist(x[1114],x[1004]))) min(dist(x[1114],x[299]),sub(1138,dist(x[1114],x[299]))) min(dist(x[1114],x[710]),sub(1138,dist(x[1114],x[710]))) min(dist(x[1114],x[427]),sub(1138,dist(x[1114],x[427]))) min(dist(x[1114],x[401]),sub(1138,dist(x[1114],x[401]))) min(dist(x[1113],x[967]),sub(1138,dist(x[1113],x[967]))) min(dist(x[1113],x[74]),sub(1138,dist(x[1113],x[74]))) min(dist(x[1113],x[924]),sub(1138,dist(x[1113],x[924]))) min(dist(x[1113],x[427]),sub(1138,dist(x[1113],x[427]))) min(dist(x[56],x[37]),sub(1138,dist(x[56],x[37]))) min(dist(x[56],x[245]),sub(1138,dist(x[56],x[245]))) min(dist(x[56],x[1079]),sub(1138,dist(x[56],x[1079]))) min(dist(x[56],x[906]),sub(1138,dist(x[56],x[906]))) min(dist(x[967],x[784]),sub(1138,dist(x[967],x[784]))) min(dist(x[967],x[731]),sub(1138,dist(x[967],x[731]))) min(dist(x[967],x[916]),sub(1138,dist(x[967],x[916]))) min(dist(x[37],x[1079]),sub(1138,dist(x[37],x[1079]))) min(dist(x[837],x[637]),sub(1138,dist(x[837],x[637]))) min(dist(x[345],x[381]),sub(1138,dist(x[345],x[381]))) min(dist(x[345],x[542]),sub(1138,dist(x[345],x[542]))) min(dist(x[950],x[1073]),sub(1138,dist(x[950],x[1073]))) min(dist(x[950],x[1109]),sub(1138,dist(x[950],x[1109]))) min(dist(x[1073],x[1109]),sub(1138,dist(x[1073],x[1109]))) min(dist(x[1109],x[215]),sub(1138,dist(x[1109],x[215]))) min(dist(x[991],x[1107]),sub(1138,dist(x[991],x[1107]))) min(dist(x[991],x[152]),sub(1138,dist(x[991],x[152]))) min(dist(x[1081],x[571]),sub(1138,dist(x[1081],x[571]))) min(dist(x[571],x[411]),sub(1138,dist(x[571],x[411]))) min(dist(x[152],x[815]),sub(1138,dist(x[152],x[815]))) min(dist(x[411],x[1070]),sub(1138,dist(x[411],x[1070]))) min(dist(x[411],x[165]),sub(1138,dist(x[411],x[165]))) min(dist(x[411],x[936]),sub(1138,dist(x[411],x[936]))) min(dist(x[411],x[990]),sub(1138,dist(x[411],x[990]))) min(dist(x[1070],x[936]),sub(1138,dist(x[1070],x[936]))) min(dist(x[1070],x[249]),sub(1138,dist(x[1070],x[249]))) min(dist(x[1070],x[328]),sub(1138,dist(x[1070],x[328]))) min(dist(x[108],x[860]),sub(1138,dist(x[108],x[860]))) min(dist(x[108],x[990]),sub(1138,dist(x[108],x[990]))) min(dist(x[108],x[688]),sub(1138,dist(x[108],x[688]))) min(dist(x[860],x[151]),sub(1138,dist(x[860],x[151]))) min(dist(x[860],x[275]),sub(1138,dist(x[860],x[275]))) min(dist(x[860],x[666]),sub(1138,dist(x[860],x[666]))) min(dist(x[151],x[777]),sub(1138,dist(x[151],x[777]))) min(dist(x[578],x[362]),sub(1138,dist(x[578],x[362]))) min(dist(x[578],x[445]),sub(1138,dist(x[578],x[445]))) min(dist(x[984],x[118]),sub(1138,dist(x[984],x[118]))) min(dist(x[118],x[6]),sub(1138,dist(x[118],x[6]))) min(dist(x[9],x[623]),sub(1138,dist(x[9],x[623]))) min(dist(x[623],x[1103]),sub(1138,dist(x[623],x[1103]))) min(dist(x[623],x[656]),sub(1138,dist(x[623],x[656]))) min(dist(x[1103],x[6]),sub(1138,dist(x[1103],x[6]))) min(dist(x[1103],x[603]),sub(1138,dist(x[1103],x[603]))) min(dist(x[6],x[700]),sub(1138,dist(x[6],x[700]))) min(dist(x[603],x[700]),sub(1138,dist(x[603],x[700]))) min(dist(x[603],x[112]),sub(1138,dist(x[603],x[112]))) min(dist(x[700],x[445]),sub(1138,dist(x[700],x[445]))) min(dist(x[700],x[856]),sub(1138,dist(x[700],x[856]))) min(dist(x[700],x[469]),sub(1138,dist(x[700],x[469]))) min(dist(x[445],x[856]),sub(1138,dist(x[445],x[856]))) min(dist(x[112],x[267]),sub(1138,dist(x[112],x[267]))) min(dist(x[956],x[315]),sub(1138,dist(x[956],x[315]))) min(dist(x[956],x[268]),sub(1138,dist(x[956],x[268]))) min(dist(x[956],x[441]),sub(1138,dist(x[956],x[441]))) min(dist(x[472],x[605]),sub(1138,dist(x[472],x[605]))) min(dist(x[472],x[315]),sub(1138,dist(x[472],x[315]))) min(dist(x[472],x[104]),sub(1138,dist(x[472],x[104]))) min(dist(x[605],x[986]),sub(1138,dist(x[605],x[986]))) min(dist(x[605],x[218]),sub(1138,dist(x[605],x[218]))) min(dist(x[315],x[438]),sub(1138,dist(x[315],x[438]))) min(dist(x[1115],x[104]),sub(1138,dist(x[1115],x[104]))) min(dist(x[1115],x[780]),sub(1138,dist(x[1115],x[780]))) min(dist(x[1115],x[1058]),sub(1138,dist(x[1115],x[1058]))) min(dist(x[104],x[509]),sub(1138,dist(x[104],x[509]))) min(dist(x[246],x[780]),sub(1138,dist(x[246],x[780]))) min(dist(x[246],x[509]),sub(1138,dist(x[246],x[509]))) min(dist(x[246],x[174]),sub(1138,dist(x[246],x[174]))) min(dist(x[944],x[509]),sub(1138,dist(x[944],x[509]))) min(dist(x[944],x[83]),sub(1138,dist(x[944],x[83]))) min(dist(x[944],x[596]),sub(1138,dist(x[944],x[596]))) min(dist(x[780],x[971]),sub(1138,dist(x[780],x[971]))) min(dist(x[971],x[1002]),sub(1138,dist(x[971],x[1002]))) min(dist(x[971],x[32]),sub(1138,dist(x[971],x[32]))) min(dist(x[1024],x[2]),sub(1138,dist(x[1024],x[2]))) min(dist(x[1024],x[1136]),sub(1138,dist(x[1024],x[1136]))) min(dist(x[946],x[986]),sub(1138,dist(x[946],x[986]))) min(dist(x[946],x[195]),sub(1138,dist(x[946],x[195]))) min(dist(x[946],x[885]),sub(1138,dist(x[946],x[885]))) min(dist(x[946],x[350]),sub(1138,dist(x[946],x[350]))) min(dist(x[986],x[119]),sub(1138,dist(x[986],x[119]))) min(dist(x[784],x[924]),sub(1138,dist(x[784],x[924]))) min(dist(x[784],x[526]),sub(1138,dist(x[784],x[526]))) min(dist(x[488],x[548]),sub(1138,dist(x[488],x[548]))) min(dist(x[548],x[1120]),sub(1138,dist(x[548],x[1120]))) min(dist(x[668],x[91]),sub(1138,dist(x[668],x[91]))) min(dist(x[428],x[268]),sub(1138,dist(x[428],x[268]))) min(dist(x[190],x[391]),sub(1138,dist(x[190],x[391]))) min(dist(x[1095],x[744]),sub(1138,dist(x[1095],x[744]))) min(dist(x[1135],x[547]),sub(1138,dist(x[1135],x[547]))) min(dist(x[911],x[955]),sub(1138,dist(x[911],x[955]))) min(dist(x[633],x[754]),sub(1138,dist(x[633],x[754]))) min(dist(x[904],x[441]),sub(1138,dist(x[904],x[441]))) min(dist(x[124],x[291]),sub(1138,dist(x[124],x[291]))) min(dist(x[838],x[220]),sub(1138,dist(x[838],x[220]))) min(dist(x[145],x[635]),sub(1138,dist(x[145],x[635]))) min(dist(x[145],x[870]),sub(1138,dist(x[145],x[870]))) min(dist(x[1010],x[933]),sub(1138,dist(x[1010],x[933]))) min(dist(x[1010],x[1080]),sub(1138,dist(x[1010],x[1080]))) min(dist(x[752],x[214]),sub(1138,dist(x[752],x[214]))) min(dist(x[752],x[195]),sub(1138,dist(x[752],x[195]))) min(dist(x[106],x[954]),sub(1138,dist(x[106],x[954]))) min(dist(x[106],x[527]),sub(1138,dist(x[106],x[527]))) min(dist(x[106],x[69]),sub(1138,dist(x[106],x[69]))) min(dist(x[106],x[336]),sub(1138,dist(x[106],x[336]))) min(dist(x[106],x[270]),sub(1138,dist(x[106],x[270]))) min(dist(x[954],x[612]),sub(1138,dist(x[954],x[612]))) min(dist(x[954],x[23]),sub(1138,dist(x[954],x[23]))) min(dist(x[954],x[962]),sub(1138,dist(x[954],x[962]))) min(dist(x[782],x[91]),sub(1138,dist(x[782],x[91]))) min(dist(x[556],x[91]),sub(1138,dist(x[556],x[91]))) min(dist(x[556],x[552]),sub(1138,dist(x[556],x[552]))) min(dist(x[556],x[391]),sub(1138,dist(x[556],x[391]))) min(dist(x[556],x[412]),sub(1138,dist(x[556],x[412]))) min(dist(x[91],x[661]),sub(1138,dist(x[91],x[661]))) min(dist(x[91],x[23]),sub(1138,dist(x[91],x[23]))) min(dist(x[91],x[883]),sub(1138,dist(x[91],x[883]))) min(dist(x[552],x[391]),sub(1138,dist(x[552],x[391]))) min(dist(x[455],x[744]),sub(1138,dist(x[455],x[744]))) min(dist(x[455],x[69]),sub(1138,dist(x[455],x[69]))) min(dist(x[527],x[899]),sub(1138,dist(x[527],x[899]))) min(dist(x[823],x[288]),sub(1138,dist(x[823],x[288]))) min(dist(x[823],x[412]),sub(1138,dist(x[823],x[412]))) min(dist(x[1046],x[96]),sub(1138,dist(x[1046],x[96]))) min(dist(x[1046],x[406]),sub(1138,dist(x[1046],x[406]))) min(dist(x[933],x[268]),sub(1138,dist(x[933],x[268]))) min(dist(x[933],x[214]),sub(1138,dist(x[933],x[214]))) min(dist(x[933],x[60]),sub(1138,dist(x[933],x[60]))) min(dist(x[268],x[755]),sub(1138,dist(x[268],x[755]))) min(dist(x[1060],x[902]),sub(1138,dist(x[1060],x[902]))) min(dist(x[1060],x[847]),sub(1138,dist(x[1060],x[847]))) min(dist(x[391],x[480]),sub(1138,dist(x[391],x[480]))) min(dist(x[1054],x[787]),sub(1138,dist(x[1054],x[787]))) min(dist(x[1054],x[96]),sub(1138,dist(x[1054],x[96]))) min(dist(x[1054],x[955]),sub(1138,dist(x[1054],x[955]))) min(dist(x[787],x[955]),sub(1138,dist(x[787],x[955]))) min(dist(x[96],x[630]),sub(1138,dist(x[96],x[630]))) min(dist(x[96],x[406]),sub(1138,dist(x[96],x[406]))) min(dist(x[480],x[868]),sub(1138,dist(x[480],x[868]))) min(dist(x[744],x[69]),sub(1138,dist(x[744],x[69]))) min(dist(x[294],x[547]),sub(1138,dist(x[294],x[547]))) min(dist(x[635],x[547]),sub(1138,dist(x[635],x[547]))) min(dist(x[635],x[870]),sub(1138,dist(x[635],x[870]))) min(dist(x[635],x[1035]),sub(1138,dist(x[635],x[1035]))) min(dist(x[547],x[755]),sub(1138,dist(x[547],x[755]))) min(dist(x[547],x[23]),sub(1138,dist(x[547],x[23]))) min(dist(x[547],x[220]),sub(1138,dist(x[547],x[220]))) min(dist(x[755],x[1045]),sub(1138,dist(x[755],x[1045]))) min(dist(x[755],x[441]),sub(1138,dist(x[755],x[441]))) min(dist(x[825],x[899]),sub(1138,dist(x[825],x[899]))) min(dist(x[612],x[899]),sub(1138,dist(x[612],x[899]))) min(dist(x[612],x[883]),sub(1138,dist(x[612],x[883]))) min(dist(x[899],x[288]),sub(1138,dist(x[899],x[288]))) min(dist(x[899],x[347]),sub(1138,dist(x[899],x[347]))) min(dist(x[899],x[69]),sub(1138,dist(x[899],x[69]))) min(dist(x[185],x[902]),sub(1138,dist(x[185],x[902]))) min(dist(x[185],x[847]),sub(1138,dist(x[185],x[847]))) min(dist(x[896],x[225]),sub(1138,dist(x[896],x[225]))) min(dist(x[690],x[138]),sub(1138,dist(x[690],x[138]))) min(dist(x[690],x[72]),sub(1138,dist(x[690],x[72]))) min(dist(x[690],x[754]),sub(1138,dist(x[690],x[754]))) min(dist(x[690],x[902]),sub(1138,dist(x[690],x[902]))) min(dist(x[661],x[225]),sub(1138,dist(x[661],x[225]))) min(dist(x[661],x[883]),sub(1138,dist(x[661],x[883]))) min(dist(x[661],x[988]),sub(1138,dist(x[661],x[988]))) min(dist(x[1045],x[754]),sub(1138,dist(x[1045],x[754]))) min(dist(x[1045],x[225]),sub(1138,dist(x[1045],x[225]))) min(dist(x[1045],x[842]),sub(1138,dist(x[1045],x[842]))) min(dist(x[412],x[847]),sub(1138,dist(x[412],x[847]))) min(dist(x[138],x[902]),sub(1138,dist(x[138],x[902]))) min(dist(x[72],x[809]),sub(1138,dist(x[72],x[809]))) min(dist(x[180],x[23]),sub(1138,dist(x[180],x[23]))) min(dist(x[180],x[98]),sub(1138,dist(x[180],x[98]))) min(dist(x[23],x[883]),sub(1138,dist(x[23],x[883]))) min(dist(x[98],x[868]),sub(1138,dist(x[98],x[868]))) min(dist(x[870],x[1035]),sub(1138,dist(x[870],x[1035]))) min(dist(x[347],x[847]),sub(1138,dist(x[347],x[847]))) min(dist(x[955],x[842]),sub(1138,dist(x[955],x[842]))) min(dist(x[955],x[918]),sub(1138,dist(x[955],x[918]))) min(dist(x[852],x[239]),sub(1138,dist(x[852],x[239]))) min(dist(x[852],x[406]),sub(1138,dist(x[852],x[406]))) min(dist(x[852],x[883]),sub(1138,dist(x[852],x[883]))) min(dist(x[902],x[809]),sub(1138,dist(x[902],x[809]))) min(dist(x[441],x[656]),sub(1138,dist(x[441],x[656]))) min(dist(x[630],x[406]),sub(1138,dist(x[630],x[406]))) min(dist(x[847],x[883]),sub(1138,dist(x[847],x[883]))) min(dist(x[291],x[988]),sub(1138,dist(x[291],x[988]))) min(dist(x[291],x[599]),sub(1138,dist(x[291],x[599]))) min(dist(x[1035],x[214]),sub(1138,dist(x[1035],x[214]))) min(dist(x[1035],x[569]),sub(1138,dist(x[1035],x[569]))) min(dist(x[214],x[569]),sub(1138,dist(x[214],x[569]))) min(dist(x[214],x[1080]),sub(1138,dist(x[214],x[1080]))) min(dist(x[214],x[195]),sub(1138,dist(x[214],x[195]))) min(dist(x[336],x[270]),sub(1138,dist(x[336],x[270]))) min(dist(x[918],x[783]),sub(1138,dist(x[918],x[783]))) min(dist(x[962],x[329]),sub(1138,dist(x[962],x[329]))) min(dist(x[329],x[211]),sub(1138,dist(x[329],x[211]))) min(dist(x[329],x[30]),sub(1138,dist(x[329],x[30]))) min(dist(x[329],x[270]),sub(1138,dist(x[329],x[270]))) min(dist(x[30],x[270]),sub(1138,dist(x[30],x[270]))) min(dist(x[49],x[285]),sub(1138,dist(x[49],x[285]))) min(dist(x[49],x[183]),sub(1138,dist(x[49],x[183]))) min(dist(x[529],x[285]),sub(1138,dist(x[529],x[285]))) min(dist(x[529],x[1001]),sub(1138,dist(x[529],x[1001]))) min(dist(x[529],x[197]),sub(1138,dist(x[529],x[197]))) min(dist(x[529],x[951]),sub(1138,dist(x[529],x[951]))) min(dist(x[529],x[379]),sub(1138,dist(x[529],x[379]))) min(dist(x[529],x[510]),sub(1138,dist(x[529],x[510]))) min(dist(x[285],x[992]),sub(1138,dist(x[285],x[992]))) min(dist(x[55],x[484]),sub(1138,dist(x[55],x[484]))) min(dist(x[55],x[35]),sub(1138,dist(x[55],x[35]))) min(dist(x[55],x[983]),sub(1138,dist(x[55],x[983]))) min(dist(x[55],x[1136]),sub(1138,dist(x[55],x[1136]))) min(dist(x[55],x[141]),sub(1138,dist(x[55],x[141]))) min(dist(x[44],x[644]),sub(1138,dist(x[44],x[644]))) min(dist(x[44],x[197]),sub(1138,dist(x[44],x[197]))) min(dist(x[644],x[197]),sub(1138,dist(x[644],x[197]))) min(dist(x[644],x[1043]),sub(1138,dist(x[644],x[1043]))) min(dist(x[426],x[1031]),sub(1138,dist(x[426],x[1031]))) min(dist(x[895],x[704]),sub(1138,dist(x[895],x[704]))) min(dist(x[895],x[778]),sub(1138,dist(x[895],x[778]))) min(dist(x[895],x[554]),sub(1138,dist(x[895],x[554]))) min(dist(x[895],x[421]),sub(1138,dist(x[895],x[421]))) min(dist(x[895],x[822]),sub(1138,dist(x[895],x[822]))) min(dist(x[895],x[558]),sub(1138,dist(x[895],x[558]))) min(dist(x[895],x[1042]),sub(1138,dist(x[895],x[1042]))) min(dist(x[895],x[199]),sub(1138,dist(x[895],x[199]))) min(dist(x[895],x[122]),sub(1138,dist(x[895],x[122]))) min(dist(x[895],x[682]),sub(1138,dist(x[895],x[682]))) min(dist(x[895],x[653]),sub(1138,dist(x[895],x[653]))) min(dist(x[895],x[687]),sub(1138,dist(x[895],x[687]))) min(dist(x[895],x[510]),sub(1138,dist(x[895],x[510]))) min(dist(x[895],x[139]),sub(1138,dist(x[895],x[139]))) min(dist(x[895],x[1092]),sub(1138,dist(x[895],x[1092]))) min(dist(x[895],x[574]),sub(1138,dist(x[895],x[574]))) min(dist(x[704],x[121]),sub(1138,dist(x[704],x[121]))) min(dist(x[704],x[587]),sub(1138,dist(x[704],x[587]))) min(dist(x[121],x[951]),sub(1138,dist(x[121],x[951]))) min(dist(x[587],x[379]),sub(1138,dist(x[587],x[379]))) min(dist(x[778],x[139]),sub(1138,dist(x[778],x[139]))) min(dist(x[583],x[1033]),sub(1138,dist(x[583],x[1033]))) min(dist(x[583],x[286]),sub(1138,dist(x[583],x[286]))) min(dist(x[1033],x[286]),sub(1138,dist(x[1033],x[286]))) min(dist(x[146],x[105]),sub(1138,dist(x[146],x[105]))) min(dist(x[725],x[421]),sub(1138,dist(x[725],x[421]))) min(dist(x[725],x[238]),sub(1138,dist(x[725],x[238]))) min(dist(x[725],x[199]),sub(1138,dist(x[725],x[199]))) min(dist(x[725],x[813]),sub(1138,dist(x[725],x[813]))) min(dist(x[1047],x[492]),sub(1138,dist(x[1047],x[492]))) min(dist(x[481],x[139]),sub(1138,dist(x[481],x[139]))) min(dist(x[481],x[960]),sub(1138,dist(x[481],x[960]))) min(dist(x[398],x[286]),sub(1138,dist(x[398],x[286]))) min(dist(x[398],x[720]),sub(1138,dist(x[398],x[720]))) min(dist(x[286],x[2]),sub(1138,dist(x[286],x[2]))) min(dist(x[286],x[737]),sub(1138,dist(x[286],x[737]))) min(dist(x[286],x[238]),sub(1138,dist(x[286],x[238]))) min(dist(x[797],x[93]),sub(1138,dist(x[797],x[93]))) min(dist(x[797],x[813]),sub(1138,dist(x[797],x[813]))) min(dist(x[797],x[1092]),sub(1138,dist(x[797],x[1092]))) min(dist(x[2],x[484]),sub(1138,dist(x[2],x[484]))) min(dist(x[2],x[574]),sub(1138,dist(x[2],x[574]))) min(dist(x[1031],x[203]),sub(1138,dist(x[1031],x[203]))) min(dist(x[737],x[199]),sub(1138,dist(x[737],x[199]))) min(dist(x[245],x[1079]),sub(1138,dist(x[245],x[1079]))) min(dist(x[245],x[609]),sub(1138,dist(x[245],x[609]))) min(dist(x[245],x[363]),sub(1138,dist(x[245],x[363]))) min(dist(x[74],x[501]),sub(1138,dist(x[74],x[501]))) min(dist(x[70],x[609]),sub(1138,dist(x[70],x[609]))) min(dist(x[70],x[906]),sub(1138,dist(x[70],x[906]))) min(dist(x[822],x[183]),sub(1138,dist(x[822],x[183]))) min(dist(x[492],x[105]),sub(1138,dist(x[492],x[105]))) min(dist(x[492],x[965]),sub(1138,dist(x[492],x[965]))) min(dist(x[492],x[194]),sub(1138,dist(x[492],x[194]))) min(dist(x[1079],x[197]),sub(1138,dist(x[1079],x[197]))) min(dist(x[1079],x[261]),sub(1138,dist(x[1079],x[261]))) min(dist(x[300],x[965]),sub(1138,dist(x[300],x[965]))) min(dist(x[197],x[558]),sub(1138,dist(x[197],x[558]))) min(dist(x[197],x[1042]),sub(1138,dist(x[197],x[1042]))) min(dist(x[197],x[313]),sub(1138,dist(x[197],x[313]))) min(dist(x[197],x[924]),sub(1138,dist(x[197],x[924]))) min(dist(x[197],x[293]),sub(1138,dist(x[197],x[293]))) min(dist(x[610],x[499]),sub(1138,dist(x[610],x[499]))) min(dist(x[610],x[678]),sub(1138,dist(x[610],x[678]))) min(dist(x[610],x[459]),sub(1138,dist(x[610],x[459]))) min(dist(x[499],x[373]),sub(1138,dist(x[499],x[373]))) min(dist(x[942],x[720]),sub(1138,dist(x[942],x[720]))) min(dist(x[942],x[199]),sub(1138,dist(x[942],x[199]))) min(dist(x[203],x[983]),sub(1138,dist(x[203],x[983]))) min(dist(x[794],x[682]),sub(1138,dist(x[794],x[682]))) min(dist(x[154],x[122]),sub(1138,dist(x[154],x[122]))) min(dist(x[422],x[379]),sub(1138,dist(x[422],x[379]))) min(dist(x[698],x[18]),sub(1138,dist(x[698],x[18]))) min(dist(x[18],x[510]),sub(1138,dist(x[18],x[510]))) min(dist(x[906],x[388]),sub(1138,dist(x[906],x[388]))) min(dist(x[261],x[363]),sub(1138,dist(x[261],x[363]))) min(dist(x[678],x[373]),sub(1138,dist(x[678],x[373]))) min(dist(x[1099],x[450]),sub(1138,dist(x[1099],x[450]))) min(dist(x[1099],x[459]),sub(1138,dist(x[1099],x[459]))) min(dist(x[1099],x[880]),sub(1138,dist(x[1099],x[880]))) min(dist(x[450],x[459]),sub(1138,dist(x[450],x[459]))) min(dist(x[776],x[1004]),sub(1138,dist(x[776],x[1004]))) min(dist(x[395],x[299]),sub(1138,dist(x[395],x[299]))) min(dist(x[501],x[401]),sub(1138,dist(x[501],x[401]))) min(dist(x[373],x[459]),sub(1138,dist(x[373],x[459]))) min(dist(x[459],x[230]),sub(1138,dist(x[459],x[230]))) min(dist(x[459],x[819]),sub(1138,dist(x[459],x[819]))) min(dist(x[459],x[299]),sub(1138,dist(x[459],x[299]))) min(dist(x[230],x[1004]),sub(1138,dist(x[230],x[1004]))) min(dist(x[924],x[731]),sub(1138,dist(x[924],x[731]))) min(dist(x[819],x[880]),sub(1138,dist(x[819],x[880]))) min(dist(x[710],x[427]),sub(1138,dist(x[710],x[427]))) min(dist(x[40],x[839]),sub(1138,dist(x[40],x[839]))) min(dist(x[759],x[48]),sub(1138,dist(x[759],x[48]))) min(dist(x[845],x[46]),sub(1138,dist(x[845],x[46]))) min(dist(x[660],x[133]),sub(1138,dist(x[660],x[133]))) min(dist(x[468],x[133]),sub(1138,dist(x[468],x[133]))) min(dist(x[839],x[46]),sub(1138,dist(x[839],x[46]))) min(dist(x[48],x[46]),sub(1138,dist(x[48],x[46]))) min(dist(x[46],x[298]),sub(1138,dist(x[46],x[298]))) min(dist(x[46],x[82]),sub(1138,dist(x[46],x[82]))) min(dist(x[46],x[1093]),sub(1138,dist(x[46],x[1093]))) min(dist(x[298],x[1093]),sub(1138,dist(x[298],x[1093]))) min(dist(x[82],x[1093]),sub(1138,dist(x[82],x[1093]))) min(dist(x[1093],x[775]),sub(1138,dist(x[1093],x[775]))) min(dist(x[1093],x[305]),sub(1138,dist(x[1093],x[305]))) min(dist(x[775],x[305]),sub(1138,dist(x[775],x[305]))) min(dist(x[305],x[907]),sub(1138,dist(x[305],x[907]))) min(dist(x[305],x[811]),sub(1138,dist(x[305],x[811]))) min(dist(x[305],x[414]),sub(1138,dist(x[305],x[414]))) min(dist(x[305],x[990]),sub(1138,dist(x[305],x[990]))) min(dist(x[907],x[608]),sub(1138,dist(x[907],x[608]))) min(dist(x[811],x[608]),sub(1138,dist(x[811],x[608]))) min(dist(x[414],x[608]),sub(1138,dist(x[414],x[608]))) min(dist(x[608],x[584]),sub(1138,dist(x[608],x[584]))) min(dist(x[608],x[306]),sub(1138,dist(x[608],x[306]))) min(dist(x[608],x[936]),sub(1138,dist(x[608],x[936]))) min(dist(x[584],x[872]),sub(1138,dist(x[584],x[872]))) min(dist(x[872],x[306]),sub(1138,dist(x[872],x[306]))) min(dist(x[306],x[133]),sub(1138,dist(x[306],x[133]))) min(dist(x[877],x[1136]),sub(1138,dist(x[877],x[1136]))) min(dist(x[765],x[912]),sub(1138,dist(x[765],x[912]))) min(dist(x[765],x[502]),sub(1138,dist(x[765],x[502]))) min(dist(x[765],x[301]),sub(1138,dist(x[765],x[301]))) min(dist(x[912],x[692]),sub(1138,dist(x[912],x[692]))) min(dist(x[912],x[1059]),sub(1138,dist(x[912],x[1059]))) min(dist(x[465],x[1059]),sub(1138,dist(x[465],x[1059]))) min(dist(x[465],x[150]),sub(1138,dist(x[465],x[150]))) min(dist(x[444],x[1076]),sub(1138,dist(x[444],x[1076]))) min(dist(x[171],x[150]),sub(1138,dist(x[171],x[150]))) min(dist(x[171],x[801]),sub(1138,dist(x[171],x[801]))) min(dist(x[981],x[430]),sub(1138,dist(x[981],x[430]))) min(dist(x[981],x[978]),sub(1138,dist(x[981],x[978]))) min(dist(x[853],x[925]),sub(1138,dist(x[853],x[925]))) min(dist(x[187],x[511]),sub(1138,dist(x[187],x[511]))) min(dist(x[903],x[224]),sub(1138,dist(x[903],x[224]))) min(dist(x[675],x[925]),sub(1138,dist(x[675],x[925]))) min(dist(x[675],x[1102]),sub(1138,dist(x[675],x[1102]))) min(dist(x[236],x[982]),sub(1138,dist(x[236],x[982]))) min(dist(x[236],x[806]),sub(1138,dist(x[236],x[806]))) min(dist(x[692],x[941]),sub(1138,dist(x[692],x[941]))) min(dist(x[692],x[287]),sub(1138,dist(x[692],x[287]))) min(dist(x[692],x[1020]),sub(1138,dist(x[692],x[1020]))) min(dist(x[692],x[309]),sub(1138,dist(x[692],x[309]))) min(dist(x[692],x[442]),sub(1138,dist(x[692],x[442]))) min(dist(x[692],x[978]),sub(1138,dist(x[692],x[978]))) min(dist(x[692],x[760]),sub(1138,dist(x[692],x[760]))) min(dist(x[692],x[511]),sub(1138,dist(x[692],x[511]))) min(dist(x[1136],x[416]),sub(1138,dist(x[1136],x[416]))) min(dist(x[936],x[249]),sub(1138,dist(x[936],x[249]))) min(dist(x[936],x[732]),sub(1138,dist(x[936],x[732]))) min(dist(x[20],x[917]),sub(1138,dist(x[20],x[917]))) min(dist(x[917],x[732]),sub(1138,dist(x[917],x[732]))) min(dist(x[1076],x[310]),sub(1138,dist(x[1076],x[310]))) min(dist(x[1076],x[429]),sub(1138,dist(x[1076],x[429]))) min(dist(x[1076],x[972]),sub(1138,dist(x[1076],x[972]))) min(dist(x[1076],x[531]),sub(1138,dist(x[1076],x[531]))) min(dist(x[1076],x[393]),sub(1138,dist(x[1076],x[393]))) min(dist(x[1076],x[71]),sub(1138,dist(x[1076],x[71]))) min(dist(x[1076],x[576]),sub(1138,dist(x[1076],x[576]))) min(dist(x[1076],x[226]),sub(1138,dist(x[1076],x[226]))) min(dist(x[150],x[496]),sub(1138,dist(x[150],x[496]))) min(dist(x[150],x[879]),sub(1138,dist(x[150],x[879]))) min(dist(x[150],x[374]),sub(1138,dist(x[150],x[374]))) min(dist(x[150],x[402]),sub(1138,dist(x[150],x[402]))) min(dist(x[150],x[423]),sub(1138,dist(x[150],x[423]))) min(dist(x[442],x[576]),sub(1138,dist(x[442],x[576]))) min(dist(x[442],x[440]),sub(1138,dist(x[442],x[440]))) min(dist(x[442],x[1064]),sub(1138,dist(x[442],x[1064]))) min(dist(x[442],x[978]),sub(1138,dist(x[442],x[978]))) min(dist(x[442],x[869]),sub(1138,dist(x[442],x[869]))) min(dist(x[442],x[589]),sub(1138,dist(x[442],x[589]))) min(dist(x[423],x[978]),sub(1138,dist(x[423],x[978]))) min(dist(x[517],x[511]),sub(1138,dist(x[517],x[511]))) min(dist(x[517],x[925]),sub(1138,dist(x[517],x[925]))) min(dist(x[430],x[978]),sub(1138,dist(x[430],x[978]))) min(dist(x[978],x[801]),sub(1138,dist(x[978],x[801]))) min(dist(x[978],x[901]),sub(1138,dist(x[978],x[901]))) min(dist(x[978],x[589]),sub(1138,dist(x[978],x[589]))) min(dist(x[978],x[21]),sub(1138,dist(x[978],x[21]))) min(dist(x[978],x[760]),sub(1138,dist(x[978],x[760]))) min(dist(x[978],x[511]),sub(1138,dist(x[978],x[511]))) min(dist(x[654],x[21]),sub(1138,dist(x[654],x[21]))) min(dist(x[654],x[963]),sub(1138,dist(x[654],x[963]))) min(dist(x[654],x[27]),sub(1138,dist(x[654],x[27]))) min(dist(x[726],x[963]),sub(1138,dist(x[726],x[963]))) min(dist(x[726],x[27]),sub(1138,dist(x[726],x[27]))) min(dist(x[471],x[364]),sub(1138,dist(x[471],x[364]))) min(dist(x[869],x[561]),sub(1138,dist(x[869],x[561]))) min(dist(x[869],x[806]),sub(1138,dist(x[869],x[806]))) min(dist(x[226],x[301]),sub(1138,dist(x[226],x[301]))) min(dist(x[21],x[925]),sub(1138,dist(x[21],x[925]))) min(dist(x[21],x[826]),sub(1138,dist(x[21],x[826]))) min(dist(x[21],x[963]),sub(1138,dist(x[21],x[963]))) min(dist(x[21],x[27]),sub(1138,dist(x[21],x[27]))) min(dist(x[1021],x[871]),sub(1138,dist(x[1021],x[871]))) min(dist(x[1021],x[79]),sub(1138,dist(x[1021],x[79]))) min(dist(x[1021],x[451]),sub(1138,dist(x[1021],x[451]))) min(dist(x[871],x[938]),sub(1138,dist(x[871],x[938]))) min(dist(x[871],x[1125]),sub(1138,dist(x[871],x[1125]))) min(dist(x[871],x[970]),sub(1138,dist(x[871],x[970]))) min(dist(x[79],x[637]),sub(1138,dist(x[79],x[637]))) min(dist(x[79],x[215]),sub(1138,dist(x[79],x[215]))) min(dist(x[79],x[182]),sub(1138,dist(x[79],x[182]))) min(dist(x[79],x[464]),sub(1138,dist(x[79],x[464]))) min(dist(x[1026],x[948]),sub(1138,dist(x[1026],x[948]))) min(dist(x[1026],x[12]),sub(1138,dist(x[1026],x[12]))) min(dist(x[848],x[252]),sub(1138,dist(x[848],x[252]))) min(dist(x[848],x[12]),sub(1138,dist(x[848],x[12]))) min(dist(x[679],x[12]),sub(1138,dist(x[679],x[12]))) min(dist(x[679],x[349]),sub(1138,dist(x[679],x[349]))) min(dist(x[262],x[12]),sub(1138,dist(x[262],x[12]))) min(dist(x[262],x[349]),sub(1138,dist(x[262],x[349]))) min(dist(x[508],x[669]),sub(1138,dist(x[508],x[669]))) min(dist(x[508],x[164]),sub(1138,dist(x[508],x[164]))) min(dist(x[1057],x[545]),sub(1138,dist(x[1057],x[545]))) min(dist(x[1057],x[11]),sub(1138,dist(x[1057],x[11]))) min(dist(x[1057],x[1098]),sub(1138,dist(x[1057],x[1098]))) min(dist(x[131],x[746]),sub(1138,dist(x[131],x[746]))) min(dist(x[131],x[460]),sub(1138,dist(x[131],x[460]))) min(dist(x[696],x[652]),sub(1138,dist(x[696],x[652]))) min(dist(x[696],x[460]),sub(1138,dist(x[696],x[460]))) min(dist(x[746],x[611]),sub(1138,dist(x[746],x[611]))) min(dist(x[746],x[3]),sub(1138,dist(x[746],x[3]))) min(dist(x[746],x[652]),sub(1138,dist(x[746],x[652]))) min(dist(x[611],x[958]),sub(1138,dist(x[611],x[958]))) min(dist(x[611],x[100]),sub(1138,dist(x[611],x[100]))) min(dist(x[964],x[593]),sub(1138,dist(x[964],x[593]))) min(dist(x[964],x[977]),sub(1138,dist(x[964],x[977]))) min(dist(x[964],x[948]),sub(1138,dist(x[964],x[948]))) min(dist(x[964],x[252]),sub(1138,dist(x[964],x[252]))) min(dist(x[12],x[540]),sub(1138,dist(x[12],x[540]))) min(dist(x[12],x[265]),sub(1138,dist(x[12],x[265]))) min(dist(x[12],x[36]),sub(1138,dist(x[12],x[36]))) min(dist(x[404],x[265]),sub(1138,dist(x[404],x[265]))) min(dist(x[14],x[1022]),sub(1138,dist(x[14],x[1022]))) min(dist(x[958],x[476]),sub(1138,dist(x[958],x[476]))) min(dist(x[958],x[376]),sub(1138,dist(x[958],x[376]))) min(dist(x[958],x[588]),sub(1138,dist(x[958],x[588]))) min(dist(x[958],x[242]),sub(1138,dist(x[958],x[242]))) min(dist(x[376],x[580]),sub(1138,dist(x[376],x[580]))) min(dist(x[376],x[307]),sub(1138,dist(x[376],x[307]))) min(dist(x[588],x[394]),sub(1138,dist(x[588],x[394]))) min(dist(x[385],x[424]),sub(1138,dist(x[385],x[424]))) min(dist(x[385],x[1098]),sub(1138,dist(x[385],x[1098]))) min(dist(x[385],x[478]),sub(1138,dist(x[385],x[478]))) min(dist(x[385],x[460]),sub(1138,dist(x[385],x[460]))) min(dist(x[424],x[242]),sub(1138,dist(x[424],x[242]))) min(dist(x[53],x[273]),sub(1138,dist(x[53],x[273]))) min(dist(x[53],x[677]),sub(1138,dist(x[53],x[677]))) min(dist(x[677],x[816]),sub(1138,dist(x[677],x[816]))) min(dist(x[677],x[125]),sub(1138,dist(x[677],x[125]))) min(dist(x[1071],x[840]),sub(1138,dist(x[1071],x[840]))) min(dist(x[816],x[436]),sub(1138,dist(x[816],x[436]))) min(dist(x[436],x[1123]),sub(1138,dist(x[436],x[1123]))) min(dist(x[142],x[25]),sub(1138,dist(x[142],x[25]))) min(dist(x[881],x[434]),sub(1138,dist(x[881],x[434]))) min(dist(x[175],x[999]),sub(1138,dist(x[175],x[999]))) min(dist(x[175],x[36]),sub(1138,dist(x[175],x[36]))) min(dist(x[242],x[1029]),sub(1138,dist(x[242],x[1029]))) min(dist(x[242],x[307]),sub(1138,dist(x[242],x[307]))) min(dist(x[307],x[570]),sub(1138,dist(x[307],x[570]))) min(dist(x[349],x[341]),sub(1138,dist(x[349],x[341]))) min(dist(x[840],x[99]),sub(1138,dist(x[840],x[99]))) min(dist(x[840],x[164]),sub(1138,dist(x[840],x[164]))) min(dist(x[99],x[581]),sub(1138,dist(x[99],x[581]))) min(dist(x[652],x[1044]),sub(1138,dist(x[652],x[1044]))) min(dist(x[65],x[223]),sub(1138,dist(x[65],x[223]))) min(dist(x[260],x[130]),sub(1138,dist(x[260],x[130]))) min(dist(x[504],x[928]),sub(1138,dist(x[504],x[928]))) min(dist(x[504],x[215]),sub(1138,dist(x[504],x[215]))) min(dist(x[504],x[1111]),sub(1138,dist(x[504],x[1111]))) min(dist(x[504],x[866]),sub(1138,dist(x[504],x[866]))) min(dist(x[504],x[474]),sub(1138,dist(x[504],x[474]))) min(dist(x[504],x[240]),sub(1138,dist(x[504],x[240]))) min(dist(x[364],x[511]),sub(1138,dist(x[364],x[511]))) min(dist(x[475],x[15]),sub(1138,dist(x[475],x[15]))) min(dist(x[475],x[464]),sub(1138,dist(x[475],x[464]))) min(dist(x[938],x[348]),sub(1138,dist(x[938],x[348]))) min(dist(x[1125],x[215]),sub(1138,dist(x[1125],x[215]))) min(dist(x[215],x[240]),sub(1138,dist(x[215],x[240]))) min(dist(x[215],x[182]),sub(1138,dist(x[215],x[182]))) min(dist(x[925],x[1102]),sub(1138,dist(x[925],x[1102]))) min(dist(x[925],x[806]),sub(1138,dist(x[925],x[806]))) min(dist(x[925],x[832]),sub(1138,dist(x[925],x[832]))) min(dist(x[1111],x[311]),sub(1138,dist(x[1111],x[311]))) min(dist(x[1111],x[932]),sub(1138,dist(x[1111],x[932]))) min(dist(x[1111],x[250]),sub(1138,dist(x[1111],x[250]))) min(dist(x[1111],x[866]),sub(1138,dist(x[1111],x[866]))) min(dist(x[1111],x[172]),sub(1138,dist(x[1111],x[172]))) min(dist(x[348],x[826]),sub(1138,dist(x[348],x[826]))) min(dist(x[311],x[182]),sub(1138,dist(x[311],x[182]))) min(dist(x[311],x[172]),sub(1138,dist(x[311],x[172]))) min(dist(x[932],x[250]),sub(1138,dist(x[932],x[250]))) min(dist(x[970],x[451]),sub(1138,dist(x[970],x[451]))) min(dist(x[1032],x[250]),sub(1138,dist(x[1032],x[250]))) min(dist(x[54],x[250]),sub(1138,dist(x[54],x[250]))) min(dist(x[876],x[866]),sub(1138,dist(x[876],x[866]))) min(dist(x[792],x[866]),sub(1138,dist(x[792],x[866]))) min(dist(x[250],x[866]),sub(1138,dist(x[250],x[866]))) min(dist(x[250],x[181]),sub(1138,dist(x[250],x[181]))) min(dist(x[866],x[474]),sub(1138,dist(x[866],x[474]))) min(dist(x[937],x[474]),sub(1138,dist(x[937],x[474]))) min(dist(x[456],x[607]),sub(1138,dist(x[456],x[607]))) min(dist(x[323],x[1008]),sub(1138,dist(x[323],x[1008]))) min(dist(x[126],x[1065]),sub(1138,dist(x[126],x[1065]))) min(dist(x[149],x[968]),sub(1138,dist(x[149],x[968]))) min(dist(x[900],x[867]),sub(1138,dist(x[900],x[867]))) min(dist(x[454],x[702]),sub(1138,dist(x[454],x[702]))) min(dist(x[454],x[640]),sub(1138,dist(x[454],x[640]))) min(dist(x[454],x[280]),sub(1138,dist(x[454],x[280]))) min(dist(x[202],x[477]),sub(1138,dist(x[202],x[477]))) min(dist(x[202],x[607]),sub(1138,dist(x[202],x[607]))) min(dist(x[202],x[1108]),sub(1138,dist(x[202],x[1108]))) min(dist(x[202],x[1065]),sub(1138,dist(x[202],x[1065]))) min(dist(x[202],x[292]),sub(1138,dist(x[202],x[292]))) min(dist(x[202],x[1085]),sub(1138,dist(x[202],x[1085]))) min(dist(x[477],x[789]),sub(1138,dist(x[477],x[789]))) min(dist(x[477],x[785]),sub(1138,dist(x[477],x[785]))) min(dist(x[477],x[530]),sub(1138,dist(x[477],x[530]))) min(dist(x[477],x[875]),sub(1138,dist(x[477],x[875]))) min(dist(x[717],x[1108]),sub(1138,dist(x[717],x[1108]))) min(dist(x[717],x[1008]),sub(1138,dist(x[717],x[1008]))) min(dist(x[717],x[670]),sub(1138,dist(x[717],x[670]))) min(dist(x[656],x[607]),sub(1138,dist(x[656],x[607]))) min(dist(x[607],x[1065]),sub(1138,dist(x[607],x[1065]))) min(dist(x[607],x[712]),sub(1138,dist(x[607],x[712]))) min(dist(x[607],x[47]),sub(1138,dist(x[607],x[47]))) min(dist(x[1108],x[351]),sub(1138,dist(x[1108],x[351]))) min(dist(x[1108],x[34]),sub(1138,dist(x[1108],x[34]))) min(dist(x[1108],x[228]),sub(1138,dist(x[1108],x[228]))) min(dist(x[1108],x[1065]),sub(1138,dist(x[1108],x[1065]))) min(dist(x[1108],x[968]),sub(1138,dist(x[1108],x[968]))) min(dist(x[1108],x[110]),sub(1138,dist(x[1108],x[110]))) min(dist(x[351],x[998]),sub(1138,dist(x[351],x[998]))) min(dist(x[351],x[217]),sub(1138,dist(x[351],x[217]))) min(dist(x[351],x[973]),sub(1138,dist(x[351],x[973]))) min(dist(x[34],x[386]),sub(1138,dist(x[34],x[386]))) min(dist(x[34],x[228]),sub(1138,dist(x[34],x[228]))) min(dist(x[34],x[1013]),sub(1138,dist(x[34],x[1013]))) min(dist(x[34],x[1022]),sub(1138,dist(x[34],x[1022]))) min(dist(x[265],x[1013]),sub(1138,dist(x[265],x[1013]))) min(dist(x[386],x[280]),sub(1138,dist(x[386],x[280]))) min(dist(x[386],x[694]),sub(1138,dist(x[386],x[694]))) min(dist(x[116],x[1013]),sub(1138,dist(x[116],x[1013]))) min(dist(x[1008],x[497]),sub(1138,dist(x[1008],x[497]))) min(dist(x[1008],x[743]),sub(1138,dist(x[1008],x[743]))) min(dist(x[497],x[198]),sub(1138,dist(x[497],x[198]))) min(dist(x[497],x[805]),sub(1138,dist(x[497],x[805]))) min(dist(x[228],x[460]),sub(1138,dist(x[228],x[460]))) min(dist(x[228],x[1039]),sub(1138,dist(x[228],x[1039]))) min(dist(x[228],x[1069]),sub(1138,dist(x[228],x[1069]))) min(dist(x[228],x[1085]),sub(1138,dist(x[228],x[1085]))) min(dist(x[228],x[110]),sub(1138,dist(x[228],x[110]))) min(dist(x[1039],x[163]),sub(1138,dist(x[1039],x[163]))) min(dist(x[1039],x[321]),sub(1138,dist(x[1039],x[321]))) min(dist(x[100],x[857]),sub(1138,dist(x[100],x[857]))) min(dist(x[100],x[920]),sub(1138,dist(x[100],x[920]))) min(dist(x[1065],x[968]),sub(1138,dist(x[1065],x[968]))) min(dist(x[968],x[867]),sub(1138,dist(x[968],x[867]))) min(dist(x[867],x[985]),sub(1138,dist(x[867],x[985]))) min(dist(x[867],x[586]),sub(1138,dist(x[867],x[586]))) min(dist(x[867],x[740]),sub(1138,dist(x[867],x[740]))) min(dist(x[867],x[884]),sub(1138,dist(x[867],x[884]))) min(dist(x[169],x[716]),sub(1138,dist(x[169],x[716]))) min(dist(x[169],x[254]),sub(1138,dist(x[169],x[254]))) min(dist(x[169],x[186]),sub(1138,dist(x[169],x[186]))) min(dist(x[1126],x[636]),sub(1138,dist(x[1126],x[636]))) min(dist(x[712],x[209]),sub(1138,dist(x[712],x[209]))) min(dist(x[712],x[292]),sub(1138,dist(x[712],x[292]))) min(dist(x[209],x[191]),sub(1138,dist(x[209],x[191]))) min(dist(x[209],x[539]),sub(1138,dist(x[209],x[539]))) min(dist(x[209],x[134]),sub(1138,dist(x[209],x[134]))) min(dist(x[209],x[59]),sub(1138,dist(x[209],x[59]))) min(dist(x[209],x[761]),sub(1138,dist(x[209],x[761]))) min(dist(x[209],x[559]),sub(1138,dist(x[209],x[559]))) min(dist(x[750],x[766]),sub(1138,dist(x[750],x[766]))) min(dist(x[750],x[647]),sub(1138,dist(x[750],x[647]))) min(dist(x[750],x[640]),sub(1138,dist(x[750],x[640]))) min(dist(x[617],x[47]),sub(1138,dist(x[617],x[47]))) min(dist(x[617],x[560]),sub(1138,dist(x[617],x[560]))) min(dist(x[617],x[910]),sub(1138,dist(x[617],x[910]))) min(dist(x[617],x[346]),sub(1138,dist(x[617],x[346]))) min(dist(x[617],x[756]),sub(1138,dist(x[617],x[756]))) min(dist(x[292],x[369]),sub(1138,dist(x[292],x[369]))) min(dist(x[292],x[1022]),sub(1138,dist(x[292],x[1022]))) min(dist(x[369],x[332]),sub(1138,dist(x[369],x[332]))) min(dist(x[369],x[621]),sub(1138,dist(x[369],x[621]))) min(dist(x[369],x[258]),sub(1138,dist(x[369],x[258]))) min(dist(x[369],x[966]),sub(1138,dist(x[369],x[966]))) min(dist(x[369],x[1086]),sub(1138,dist(x[369],x[1086]))) min(dist(x[369],x[229]),sub(1138,dist(x[369],x[229]))) min(dist(x[369],x[831]),sub(1138,dist(x[369],x[831]))) min(dist(x[369],x[167]),sub(1138,dist(x[369],x[167]))) min(dist(x[369],x[691]),sub(1138,dist(x[369],x[691]))) min(dist(x[369],x[271]),sub(1138,dist(x[369],x[271]))) min(dist(x[369],x[888]),sub(1138,dist(x[369],x[888]))) min(dist(x[369],x[33]),sub(1138,dist(x[369],x[33]))) min(dist(x[1022],x[89]),sub(1138,dist(x[1022],x[89]))) min(dist(x[1022],x[1085]),sub(1138,dist(x[1022],x[1085]))) min(dist(x[1022],x[641]),sub(1138,dist(x[1022],x[641]))) min(dist(x[89],x[120]),sub(1138,dist(x[89],x[120]))) min(dist(x[1085],x[125]),sub(1138,dist(x[1085],x[125]))) min(dist(x[1085],x[672]),sub(1138,dist(x[1085],x[672]))) min(dist(x[1085],x[210]),sub(1138,dist(x[1085],x[210]))) min(dist(x[1085],x[641]),sub(1138,dist(x[1085],x[641]))) min(dist(x[672],x[647]),sub(1138,dist(x[672],x[647]))) min(dist(x[672],x[280]),sub(1138,dist(x[672],x[280]))) min(dist(x[672],x[206]),sub(1138,dist(x[672],x[206]))) min(dist(x[672],x[799]),sub(1138,dist(x[672],x[799]))) min(dist(x[672],x[791]),sub(1138,dist(x[672],x[791]))) min(dist(x[743],x[264]),sub(1138,dist(x[743],x[264]))) min(dist(x[1110],x[130]),sub(1138,dist(x[1110],x[130]))) min(dist(x[641],x[130]),sub(1138,dist(x[641],x[130]))) min(dist(x[641],x[164]),sub(1138,dist(x[641],x[164]))) min(dist(x[641],x[469]),sub(1138,dist(x[641],x[469]))) min(dist(x[130],x[223]),sub(1138,dist(x[130],x[223]))) min(dist(x[16],x[864]),sub(1138,dist(x[16],x[864]))) min(dist(x[705],x[279]),sub(1138,dist(x[705],x[279]))) min(dist(x[173],x[419]),sub(1138,dist(x[173],x[419]))) min(dist(x[864],x[703]),sub(1138,dist(x[864],x[703]))) min(dist(x[864],x[1009]),sub(1138,dist(x[864],x[1009]))) min(dist(x[864],x[419]),sub(1138,dist(x[864],x[419]))) min(dist(x[703],x[836]),sub(1138,dist(x[703],x[836]))) min(dist(x[703],x[810]),sub(1138,dist(x[703],x[810]))) min(dist(x[670],x[505]),sub(1138,dist(x[670],x[505]))) min(dist(x[670],x[15]),sub(1138,dist(x[670],x[15]))) min(dist(x[332],x[353]),sub(1138,dist(x[332],x[353]))) min(dist(x[332],x[614]),sub(1138,dist(x[332],x[614]))) min(dist(x[1009],x[408]),sub(1138,dist(x[1009],x[408]))) min(dist(x[1009],x[952]),sub(1138,dist(x[1009],x[952]))) min(dist(x[1009],x[36]),sub(1138,dist(x[1009],x[36]))) min(dist(x[1009],x[419]),sub(1138,dist(x[1009],x[419]))) min(dist(x[408],x[482]),sub(1138,dist(x[408],x[482]))) min(dist(x[408],x[790]),sub(1138,dist(x[408],x[790]))) min(dist(x[408],x[1061]),sub(1138,dist(x[408],x[1061]))) min(dist(x[408],x[706]),sub(1138,dist(x[408],x[706]))) min(dist(x[952],x[836]),sub(1138,dist(x[952],x[836]))) min(dist(x[836],x[536]),sub(1138,dist(x[836],x[536]))) min(dist(x[836],x[123]),sub(1138,dist(x[836],x[123]))) min(dist(x[836],x[634]),sub(1138,dist(x[836],x[634]))) min(dist(x[836],x[1128]),sub(1138,dist(x[836],x[1128]))) min(dist(x[836],x[162]),sub(1138,dist(x[836],x[162]))) min(dist(x[836],x[272]),sub(1138,dist(x[836],x[272]))) min(dist(x[836],x[94]),sub(1138,dist(x[836],x[94]))) min(dist(x[482],x[790]),sub(1138,dist(x[482],x[790]))) min(dist(x[810],x[123]),sub(1138,dist(x[810],x[123]))) min(dist(x[505],x[1132]),sub(1138,dist(x[505],x[1132]))) min(dist(x[505],x[419]),sub(1138,dist(x[505],x[419]))) min(dist(x[1132],x[279]),sub(1138,dist(x[1132],x[279]))) min(dist(x[279],x[111]),sub(1138,dist(x[279],x[111]))) min(dist(x[1007],x[111]),sub(1138,dist(x[1007],x[111]))) min(dist(x[419],x[111]),sub(1138,dist(x[419],x[111]))) min(dist(x[636],x[579]),sub(1138,dist(x[636],x[579]))) min(dist(x[636],x[805]),sub(1138,dist(x[636],x[805]))) min(dist(x[513],x[57]),sub(1138,dist(x[513],x[57]))) min(dist(x[290],x[790]),sub(1138,dist(x[290],x[790]))) min(dist(x[931],x[64]),sub(1138,dist(x[931],x[64]))) min(dist(x[663],x[80]),sub(1138,dist(x[663],x[80]))) min(dist(x[854],x[807]),sub(1138,dist(x[854],x[807]))) min(dist(x[367],x[798]),sub(1138,dist(x[367],x[798]))) min(dist(x[1018],x[985]),sub(1138,dist(x[1018],x[985]))) min(dist(x[1018],x[372]),sub(1138,dist(x[1018],x[372]))) min(dist(x[490],x[143]),sub(1138,dist(x[490],x[143]))) min(dist(x[490],x[884]),sub(1138,dist(x[490],x[884]))) min(dist(x[490],x[1027]),sub(1138,dist(x[490],x[1027]))) min(dist(x[47],x[910]),sub(1138,dist(x[47],x[910]))) min(dist(x[790],x[762]),sub(1138,dist(x[790],x[762]))) min(dist(x[790],x[26]),sub(1138,dist(x[790],x[26]))) min(dist(x[790],x[80]),sub(1138,dist(x[790],x[80]))) min(dist(x[790],x[541]),sub(1138,dist(x[790],x[541]))) min(dist(x[790],x[1118]),sub(1138,dist(x[790],x[1118]))) min(dist(x[762],x[528]),sub(1138,dist(x[762],x[528]))) min(dist(x[798],x[64]),sub(1138,dist(x[798],x[64]))) min(dist(x[798],x[807]),sub(1138,dist(x[798],x[807]))) min(dist(x[798],x[346]),sub(1138,dist(x[798],x[346]))) min(dist(x[798],x[276]),sub(1138,dist(x[798],x[276]))) min(dist(x[560],x[910]),sub(1138,dist(x[560],x[910]))) min(dist(x[560],x[756]),sub(1138,dist(x[560],x[756]))) min(dist(x[196],x[788]),sub(1138,dist(x[196],x[788]))) min(dist(x[196],x[134]),sub(1138,dist(x[196],x[134]))) min(dist(x[788],x[789]),sub(1138,dist(x[788],x[789]))) min(dist(x[788],x[530]),sub(1138,dist(x[788],x[530]))) min(dist(x[788],x[1088]),sub(1138,dist(x[788],x[1088]))) min(dist(x[77],x[748]),sub(1138,dist(x[77],x[748]))) min(dist(x[528],x[1040]),sub(1138,dist(x[528],x[1040]))) min(dist(x[528],x[751]),sub(1138,dist(x[528],x[751]))) min(dist(x[833],x[947]),sub(1138,dist(x[833],x[947]))) min(dist(x[833],x[748]),sub(1138,dist(x[833],x[748]))) min(dist(x[565],x[1074]),sub(1138,dist(x[565],x[1074]))) min(dist(x[723],x[947]),sub(1138,dist(x[723],x[947]))) min(dist(x[723],x[50]),sub(1138,dist(x[723],x[50]))) min(dist(x[1074],x[132]),sub(1138,dist(x[1074],x[132]))) min(dist(x[66],x[399]),sub(1138,dist(x[66],x[399]))) min(dist(x[976],x[344]),sub(1138,dist(x[976],x[344]))) min(dist(x[156],x[1062]),sub(1138,dist(x[156],x[1062]))) min(dist(x[786],x[748]),sub(1138,dist(x[786],x[748]))) min(dist(x[786],x[846]),sub(1138,dist(x[786],x[846]))) min(dist(x[786],x[789]),sub(1138,dist(x[786],x[789]))) min(dist(x[1090],x[975]),sub(1138,dist(x[1090],x[975]))) min(dist(x[1062],x[132]),sub(1138,dist(x[1062],x[132]))) min(dist(x[1062],x[26]),sub(1138,dist(x[1062],x[26]))) min(dist(x[132],x[157]),sub(1138,dist(x[132],x[157]))) min(dist(x[132],x[453]),sub(1138,dist(x[132],x[453]))) min(dist(x[157],x[878]),sub(1138,dist(x[157],x[878]))) min(dist(x[846],x[344]),sub(1138,dist(x[846],x[344]))) min(dist(x[846],x[97]),sub(1138,dist(x[846],x[97]))) min(dist(x[846],x[383]),sub(1138,dist(x[846],x[383]))) min(dist(x[344],x[129]),sub(1138,dist(x[344],x[129]))) min(dist(x[344],x[601]),sub(1138,dist(x[344],x[601]))) min(dist(x[97],x[789]),sub(1138,dist(x[97],x[789]))) min(dist(x[893],x[521]),sub(1138,dist(x[893],x[521]))) min(dist(x[1100],x[521]),sub(1138,dist(x[1100],x[521]))) min(dist(x[1100],x[763]),sub(1138,dist(x[1100],x[763]))) min(dist(x[785],x[134]),sub(1138,dist(x[785],x[134]))) min(dist(x[399],x[601]),sub(1138,dist(x[399],x[601]))) min(dist(x[676],x[629]),sub(1138,dist(x[676],x[629]))) min(dist(x[980],x[81]),sub(1138,dist(x[980],x[81]))) min(dist(x[980],x[217]),sub(1138,dist(x[980],x[217]))) min(dist(x[998],x[927]),sub(1138,dist(x[998],x[927]))) min(dist(x[927],x[76]),sub(1138,dist(x[927],x[76]))) min(dist(x[1061],x[849]),sub(1138,dist(x[1061],x[849]))) min(dist(x[1061],x[443]),sub(1138,dist(x[1061],x[443]))) min(dist(x[337],x[714]),sub(1138,dist(x[337],x[714]))) min(dist(x[337],x[830]),sub(1138,dist(x[337],x[830]))) min(dist(x[506],x[217]),sub(1138,dist(x[506],x[217]))) min(dist(x[506],x[594]),sub(1138,dist(x[506],x[594]))) min(dist(x[849],x[466]),sub(1138,dist(x[849],x[466]))) min(dist(x[714],x[177]),sub(1138,dist(x[714],x[177]))) min(dist(x[564],x[86]),sub(1138,dist(x[564],x[86]))) min(dist(x[564],x[177]),sub(1138,dist(x[564],x[177]))) min(dist(x[537],x[217]),sub(1138,dist(x[537],x[217]))) min(dist(x[573],x[117]),sub(1138,dist(x[573],x[117]))) min(dist(x[573],x[594]),sub(1138,dist(x[573],x[594]))) min(dist(x[81],x[314]),sub(1138,dist(x[81],x[314]))) min(dist(x[81],x[551]),sub(1138,dist(x[81],x[551]))) min(dist(x[343],x[117]),sub(1138,dist(x[343],x[117]))) min(dist(x[343],x[177]),sub(1138,dist(x[343],x[177]))) min(dist(x[343],x[807]),sub(1138,dist(x[343],x[807]))) min(dist(x[76],x[86]),sub(1138,dist(x[76],x[86]))) min(dist(x[76],x[830]),sub(1138,dist(x[76],x[830]))) min(dist(x[177],x[278]),sub(1138,dist(x[177],x[278]))) min(dist(x[278],x[795]),sub(1138,dist(x[278],x[795]))) min(dist(x[1034],x[258]),sub(1138,dist(x[1034],x[258]))) min(dist(x[1034],x[425]),sub(1138,dist(x[1034],x[425]))) min(dist(x[389],x[333]),sub(1138,dist(x[389],x[333]))) min(dist(x[389],x[522]),sub(1138,dist(x[389],x[522]))) min(dist(x[730],x[1012]),sub(1138,dist(x[730],x[1012]))) min(dist(x[730],x[935]),sub(1138,dist(x[730],x[935]))) min(dist(x[621],x[155]),sub(1138,dist(x[621],x[155]))) min(dist(x[1050],x[135]),sub(1138,dist(x[1050],x[135]))) min(dist(x[1050],x[606]),sub(1138,dist(x[1050],x[606]))) min(dist(x[624],x[229]),sub(1138,dist(x[624],x[229]))) min(dist(x[624],x[334]),sub(1138,dist(x[624],x[334]))) min(dist(x[333],x[400]),sub(1138,dist(x[333],x[400]))) min(dist(x[650],x[1063]),sub(1138,dist(x[650],x[1063]))) min(dist(x[650],x[61]),sub(1138,dist(x[650],x[61]))) min(dist(x[258],x[400]),sub(1138,dist(x[258],x[400]))) min(dist(x[258],x[966]),sub(1138,dist(x[258],x[966]))) min(dist(x[258],x[861]),sub(1138,dist(x[258],x[861]))) min(dist(x[258],x[1086]),sub(1138,dist(x[258],x[1086]))) min(dist(x[258],x[764]),sub(1138,dist(x[258],x[764]))) min(dist(x[258],x[355]),sub(1138,dist(x[258],x[355]))) min(dist(x[400],x[649]),sub(1138,dist(x[400],x[649]))) min(dist(x[512],x[167]),sub(1138,dist(x[512],x[167]))) min(dist(x[512],x[1037]),sub(1138,dist(x[512],x[1037]))) min(dist(x[235],x[662]),sub(1138,dist(x[235],x[662]))) min(dist(x[235],x[213]),sub(1138,dist(x[235],x[213]))) min(dist(x[943],x[135]),sub(1138,dist(x[943],x[135]))) min(dist(x[662],x[334]),sub(1138,dist(x[662],x[334]))) min(dist(x[1066],x[244]),sub(1138,dist(x[1066],x[244]))) min(dist(x[1066],x[229]),sub(1138,dist(x[1066],x[229]))) min(dist(x[1088],x[167]),sub(1138,dist(x[1088],x[167]))) min(dist(x[863],x[850]),sub(1138,dist(x[863],x[850]))) min(dist(x[863],x[604]),sub(1138,dist(x[863],x[604]))) min(dist(x[563],x[167]),sub(1138,dist(x[563],x[167]))) min(dist(x[425],x[229]),sub(1138,dist(x[425],x[229]))) min(dist(x[1012],x[707]),sub(1138,dist(x[1012],x[707]))) min(dist(x[213],x[619]),sub(1138,dist(x[213],x[619]))) min(dist(x[861],x[600]),sub(1138,dist(x[861],x[600]))) min(dist(x[575],x[935]),sub(1138,dist(x[575],x[935]))) min(dist(x[485],x[817]),sub(1138,dist(x[485],x[817]))) min(dist(x[485],x[604]),sub(1138,dist(x[485],x[604]))) min(dist(x[1063],x[447]),sub(1138,dist(x[1063],x[447]))) min(dist(x[244],x[817]),sub(1138,dist(x[244],x[817]))) min(dist(x[229],x[831]),sub(1138,dist(x[229],x[831]))) min(dist(x[229],x[619]),sub(1138,dist(x[229],x[619]))) min(dist(x[229],x[498]),sub(1138,dist(x[229],x[498]))) min(dist(x[229],x[850]),sub(1138,dist(x[229],x[850]))) min(dist(x[229],x[681]),sub(1138,dist(x[229],x[681]))) min(dist(x[229],x[604]),sub(1138,dist(x[229],x[604]))) min(dist(x[229],x[447]),sub(1138,dist(x[229],x[447]))) min(dist(x[387],x[768]),sub(1138,dist(x[387],x[768]))) min(dist(x[387],x[1101]),sub(1138,dist(x[387],x[1101]))) min(dist(x[768],x[850]),sub(1138,dist(x[768],x[850]))) min(dist(x[764],x[770]),sub(1138,dist(x[764],x[770]))) min(dist(x[167],x[135]),sub(1138,dist(x[167],x[135]))) min(dist(x[167],x[155]),sub(1138,dist(x[167],x[155]))) min(dist(x[167],x[543]),sub(1138,dist(x[167],x[543]))) min(dist(x[518],x[33]),sub(1138,dist(x[518],x[33]))) min(dist(x[518],x[1037]),sub(1138,dist(x[518],x[1037]))) min(dist(x[600],x[642]),sub(1138,dist(x[600],x[642]))) min(dist(x[844],x[486]),sub(1138,dist(x[844],x[486]))) min(dist(x[295],x[486]),sub(1138,dist(x[295],x[486]))) min(dist(x[127],x[457]),sub(1138,dist(x[127],x[457]))) min(dist(x[688],x[523]),sub(1138,dist(x[688],x[523]))) min(dist(x[688],x[335]),sub(1138,dist(x[688],x[335]))) min(dist(x[335],x[486]),sub(1138,dist(x[335],x[486]))) min(dist(x[335],x[439]),sub(1138,dist(x[335],x[439]))) min(dist(x[335],x[416]),sub(1138,dist(x[335],x[416]))) min(dist(x[335],x[779]),sub(1138,dist(x[335],x[779]))) min(dist(x[335],x[141]),sub(1138,dist(x[335],x[141]))) min(dist(x[486],x[957]),sub(1138,dist(x[486],x[957]))) min(dist(x[666],x[457]),sub(1138,dist(x[666],x[457]))) min(dist(x[666],x[439]),sub(1138,dist(x[666],x[439]))) min(dist(x[666],x[263]),sub(1138,dist(x[666],x[263]))) min(dist(x[457],x[282]),sub(1138,dist(x[457],x[282]))) min(dist(x[457],x[222]),sub(1138,dist(x[457],x[222]))) min(dist(x[957],x[222]),sub(1138,dist(x[957],x[222]))) min(dist(x[439],x[222]),sub(1138,dist(x[439],x[222]))) min(dist(x[263],x[908]),sub(1138,dist(x[263],x[908]))) min(dist(x[416],x[779]),sub(1138,dist(x[416],x[779]))) min(dist(x[433],x[474]),sub(1138,dist(x[433],x[474]))) min(dist(x[474],x[832]),sub(1138,dist(x[474],x[832]))) min(dist(x[240],x[182]),sub(1138,dist(x[240],x[182]))) min(dist(x[277],x[464]),sub(1138,dist(x[277],x[464]))) min(dist(x[277],x[181]),sub(1138,dist(x[277],x[181]))) min(dist(x[1130],x[806]),sub(1138,dist(x[1130],x[806]))) min(dist(x[51],x[806]),sub(1138,dist(x[51],x[806]))) min(dist(x[806],x[224]),sub(1138,dist(x[806],x[224]))) min(dist(x[806],x[181]),sub(1138,dist(x[806],x[181]))) min(dist(x[963],x[27]),sub(1138,dist(x[963],x[27]))) min(dist(x[1133],x[464]),sub(1138,dist(x[1133],x[464]))) min(dist(x[1127],x[464]),sub(1138,dist(x[1127],x[464]))) min(dist(x[432],x[464]),sub(1138,dist(x[432],x[464]))) min(dist(x[88],x[464]),sub(1138,dist(x[88],x[464]))) min(dist(x[10],x[464]),sub(1138,dist(x[10],x[464]))) min(dist(x[1017],x[464]),sub(1138,dist(x[1017],x[464]))) min(dist(x[464],x[381]),sub(1138,dist(x[464],x[381]))) min(dist(x[464],x[181]),sub(1138,dist(x[464],x[181]))) min(dist(x[359],x[397]),sub(1138,dist(x[359],x[397]))) min(dist(x[359],x[451]),sub(1138,dist(x[359],x[451]))) min(dist(x[397],x[451]),sub(1138,dist(x[397],x[451]))) min(dist(x[458],x[646]),sub(1138,dist(x[458],x[646]))) min(dist(x[458],x[451]),sub(1138,dist(x[458],x[451]))) min(dist(x[646],x[451]),sub(1138,dist(x[646],x[451]))) min(dist(x[361],x[195]),sub(1138,dist(x[361],x[195]))) min(dist(x[1052],x[218]),sub(1138,dist(x[1052],x[218]))) min(dist(x[922],x[195]),sub(1138,dist(x[922],x[195]))) min(dist(x[284],x[218]),sub(1138,dist(x[284],x[218]))) min(dist(x[953],x[648]),sub(1138,dist(x[953],x[648]))) min(dist(x[1058],x[1075]),sub(1138,dist(x[1058],x[1075]))) min(dist(x[1058],x[218]),sub(1138,dist(x[1058],x[218]))) min(dist(x[1058],x[648]),sub(1138,dist(x[1058],x[648]))) min(dist(x[1075],x[103]),sub(1138,dist(x[1075],x[103]))) min(dist(x[1075],x[841]),sub(1138,dist(x[1075],x[841]))) min(dist(x[218],x[195]),sub(1138,dist(x[218],x[195]))) min(dist(x[195],x[1112]),sub(1138,dist(x[195],x[1112]))) min(dist(x[648],x[1025]),sub(1138,dist(x[648],x[1025]))) min(dist(x[885],x[1112]),sub(1138,dist(x[885],x[1112]))) min(dist(x[317],x[507]),sub(1138,dist(x[317],x[507]))) min(dist(x[317],x[591]),sub(1138,dist(x[317],x[591]))) min(dist(x[507],x[160]),sub(1138,dist(x[507],x[160]))) min(dist(x[103],x[352]),sub(1138,dist(x[103],x[352]))) min(dist(x[418],x[1016]),sub(1138,dist(x[418],x[1016]))) min(dist(x[418],x[841]),sub(1138,dist(x[418],x[841]))) min(dist(x[259],x[160]),sub(1138,dist(x[259],x[160]))) min(dist(x[259],x[221]),sub(1138,dist(x[259],x[221]))) min(dist(x[29],x[160]),sub(1138,dist(x[29],x[160]))) min(dist(x[29],x[342]),sub(1138,dist(x[29],x[342]))) min(dist(x[60],x[577]),sub(1138,dist(x[60],x[577]))) min(dist(x[1025],x[160]),sub(1138,dist(x[1025],x[160]))) min(dist(x[639],x[174]),sub(1138,dist(x[639],x[174]))) min(dist(x[174],x[657]),sub(1138,dist(x[174],x[657]))) min(dist(x[174],x[193]),sub(1138,dist(x[174],x[193]))) min(dist(x[221],x[803]),sub(1138,dist(x[221],x[803]))) min(dist(x[657],x[8]),sub(1138,dist(x[657],x[8]))) min(dist(x[8],x[437]),sub(1138,dist(x[8],x[437]))) min(dist(x[8],x[479]),sub(1138,dist(x[8],x[479]))) min(dist(x[586],x[995]),sub(1138,dist(x[586],x[995]))) min(dist(x[602],x[479]),sub(1138,dist(x[602],x[479]))) min(dist(x[579],x[1067]),sub(1138,dist(x[579],x[1067]))) min(dist(x[579],x[805]),sub(1138,dist(x[579],x[805]))) min(dist(x[579],x[620]),sub(1138,dist(x[579],x[620]))) min(dist(x[579],x[884]),sub(1138,dist(x[579],x[884]))) min(dist(x[1124],x[64]),sub(1138,dist(x[1124],x[64]))) min(dist(x[1124],x[973]),sub(1138,dist(x[1124],x[973]))) min(dist(x[64],x[973]),sub(1138,dist(x[64],x[973]))) min(dist(x[64],x[807]),sub(1138,dist(x[64],x[807]))) min(dist(x[64],x[346]),sub(1138,dist(x[64],x[346]))) min(dist(x[64],x[745]),sub(1138,dist(x[64],x[745]))) min(dist(x[368],x[582]),sub(1138,dist(x[368],x[582]))) min(dist(x[368],x[805]),sub(1138,dist(x[368],x[805]))) min(dist(x[368],x[264]),sub(1138,dist(x[368],x[264]))) min(dist(x[253],x[740]),sub(1138,dist(x[253],x[740]))) min(dist(x[740],x[910]),sub(1138,dist(x[740],x[910]))) min(dist(x[740],x[546]),sub(1138,dist(x[740],x[546]))) min(dist(x[910],x[346]),sub(1138,dist(x[910],x[346]))) min(dist(x[910],x[535]),sub(1138,dist(x[910],x[535]))) min(dist(x[26],x[80]),sub(1138,dist(x[26],x[80]))) min(dist(x[372],x[884]),sub(1138,dist(x[372],x[884]))) min(dist(x[57],x[143]),sub(1138,dist(x[57],x[143]))) min(dist(x[57],x[24]),sub(1138,dist(x[57],x[24]))) min(dist(x[57],x[807]),sub(1138,dist(x[57],x[807]))) min(dist(x[57],x[346]),sub(1138,dist(x[57],x[346]))) min(dist(x[57],x[884]),sub(1138,dist(x[57],x[884]))) min(dist(x[143],x[136]),sub(1138,dist(x[143],x[136]))) min(dist(x[546],x[535]),sub(1138,dist(x[546],x[535]))) min(dist(x[24],x[102]),sub(1138,dist(x[24],x[102]))) min(dist(x[24],x[807]),sub(1138,dist(x[24],x[807]))) min(dist(x[24],x[820]),sub(1138,dist(x[24],x[820]))) min(dist(x[102],x[795]),sub(1138,dist(x[102],x[795]))) min(dist(x[198],x[316]),sub(1138,dist(x[198],x[316]))) min(dist(x[198],x[805]),sub(1138,dist(x[198],x[805]))) min(dist(x[930],x[276]),sub(1138,dist(x[930],x[276]))) min(dist(x[930],x[1129]),sub(1138,dist(x[930],x[1129]))) min(dist(x[582],x[812]),sub(1138,dist(x[582],x[812]))) min(dist(x[582],x[92]),sub(1138,dist(x[582],x[92]))) min(dist(x[812],x[805]),sub(1138,dist(x[812],x[805]))) min(dist(x[812],x[264]),sub(1138,dist(x[812],x[264]))) min(dist(x[807],x[276]),sub(1138,dist(x[807],x[276]))) min(dist(x[346],x[673]),sub(1138,dist(x[346],x[673]))) min(dist(x[346],x[756]),sub(1138,dist(x[346],x[756]))) min(dist(x[346],x[549]),sub(1138,dist(x[346],x[549]))) min(dist(x[346],x[997]),sub(1138,dist(x[346],x[997]))) min(dist(x[673],x[693]),sub(1138,dist(x[673],x[693]))) min(dist(x[884],x[491]),sub(1138,dist(x[884],x[491]))) min(dist(x[756],x[170]),sub(1138,dist(x[756],x[170]))) min(dist(x[549],x[153]),sub(1138,dist(x[549],x[153]))) min(dist(x[686],x[339]),sub(1138,dist(x[686],x[339]))) min(dist(x[251],x[772]),sub(1138,dist(x[251],x[772]))) min(dist(x[613],x[495]),sub(1138,dist(x[613],x[495]))) min(dist(x[647],x[859]),sub(1138,dist(x[647],x[859]))) min(dist(x[1078],x[1131]),sub(1138,dist(x[1078],x[1131]))) min(dist(x[1078],x[888]),sub(1138,dist(x[1078],x[888]))) min(dist(x[892],x[614]),sub(1138,dist(x[892],x[614]))) min(dist(x[1077],x[120]),sub(1138,dist(x[1077],x[120]))) min(dist(x[1077],x[1119]),sub(1138,dist(x[1077],x[1119]))) min(dist(x[1077],x[665]),sub(1138,dist(x[1077],x[665]))) min(dist(x[243],x[1117]),sub(1138,dist(x[243],x[1117]))) min(dist(x[243],x[614]),sub(1138,dist(x[243],x[614]))) min(dist(x[243],x[888]),sub(1138,dist(x[243],x[888]))) min(dist(x[431],x[553]),sub(1138,dist(x[431],x[553]))) min(dist(x[431],x[1118]),sub(1138,dist(x[431],x[1118]))) min(dist(x[553],x[824]),sub(1138,dist(x[553],x[824]))) min(dist(x[553],x[107]),sub(1138,dist(x[553],x[107]))) min(dist(x[640],x[500]),sub(1138,dist(x[640],x[500]))) min(dist(x[339],x[915]),sub(1138,dist(x[339],x[915]))) min(dist(x[339],x[495]),sub(1138,dist(x[339],x[495]))) min(dist(x[339],x[191]),sub(1138,dist(x[339],x[191]))) min(dist(x[855],x[396]),sub(1138,dist(x[855],x[396]))) min(dist(x[855],x[120]),sub(1138,dist(x[855],x[120]))) min(dist(x[855],x[446]),sub(1138,dist(x[855],x[446]))) min(dist(x[365],x[92]),sub(1138,dist(x[365],x[92]))) min(dist(x[689],x[742]),sub(1138,dist(x[689],x[742]))) min(dist(x[689],x[461]),sub(1138,dist(x[689],x[461]))) min(dist(x[689],x[384]),sub(1138,dist(x[689],x[384]))) min(dist(x[1002],x[728]),sub(1138,dist(x[1002],x[728]))) min(dist(x[1002],x[858]),sub(1138,dist(x[1002],x[858]))) min(dist(x[32],x[728]),sub(1138,dist(x[32],x[728]))) min(dist(x[32],x[544]),sub(1138,dist(x[32],x[544]))) min(dist(x[616],x[532]),sub(1138,dist(x[616],x[532]))) min(dist(x[616],x[308]),sub(1138,dist(x[616],x[308]))) min(dist(x[631],x[515]),sub(1138,dist(x[631],x[515]))) min(dist(x[631],x[308]),sub(1138,dist(x[631],x[308]))) min(dist(x[728],x[435]),sub(1138,dist(x[728],x[435]))) min(dist(x[405],x[319]),sub(1138,dist(x[405],x[319]))) min(dist(x[405],x[384]),sub(1138,dist(x[405],x[384]))) min(dist(x[403],x[1049]),sub(1138,dist(x[403],x[1049]))) min(dist(x[403],x[1089]),sub(1138,dist(x[403],x[1089]))) min(dist(x[0],x[1083]),sub(1138,dist(x[0],x[1083]))) min(dist(x[0],x[308]),sub(1138,dist(x[0],x[308]))) min(dist(x[461],x[713]),sub(1138,dist(x[461],x[713]))) min(dist(x[461],x[232]),sub(1138,dist(x[461],x[232]))) min(dist(x[520],x[695]),sub(1138,dist(x[520],x[695]))) min(dist(x[695],x[39]),sub(1138,dist(x[695],x[39]))) min(dist(x[358],x[19]),sub(1138,dist(x[358],x[19]))) min(dist(x[358],x[58]),sub(1138,dist(x[358],x[58]))) min(dist(x[358],x[1]),sub(1138,dist(x[358],x[1]))) min(dist(x[28],x[709]),sub(1138,dist(x[28],x[709]))) min(dist(x[28],x[39]),sub(1138,dist(x[28],x[39]))) min(dist(x[166],x[208]),sub(1138,dist(x[166],x[208]))) min(dist(x[166],x[462]),sub(1138,dist(x[166],x[462]))) min(dist(x[1106],x[626]),sub(1138,dist(x[1106],x[626]))) min(dist(x[1106],x[308]),sub(1138,dist(x[1106],x[308]))) min(dist(x[85],x[325]),sub(1138,dist(x[85],x[325]))) min(dist(x[462],x[39]),sub(1138,dist(x[462],x[39]))) min(dist(x[232],x[494]),sub(1138,dist(x[232],x[494]))) min(dist(x[1089],x[58]),sub(1138,dist(x[1089],x[58]))) min(dist(x[58],x[308]),sub(1138,dist(x[58],x[308]))) min(dist(x[1],x[1000]),sub(1138,dist(x[1],x[1000]))) min(dist(x[1],x[308]),sub(1138,dist(x[1],x[308]))) min(dist(x[205],x[308]),sub(1138,dist(x[205],x[308]))) min(dist(x[205],x[83]),sub(1138,dist(x[205],x[83]))) min(dist(x[989],x[562]),sub(1138,dist(x[989],x[562]))) min(dist(x[658],x[308]),sub(1138,dist(x[658],x[308]))) min(dist(x[658],x[638]),sub(1138,dist(x[658],x[638]))) min(dist(x[658],x[83]),sub(1138,dist(x[658],x[83]))) min(dist(x[308],x[452]),sub(1138,dist(x[308],x[452]))) min(dist(x[452],x[638]),sub(1138,dist(x[452],x[638]))) min(dist(x[452],x[83]),sub(1138,dist(x[452],x[83]))) min(dist(x[241],x[596]),sub(1138,dist(x[241],x[596]))) min(dist(x[39],x[596]),sub(1138,dist(x[39],x[596]))) min(dist(x[384],x[562]),sub(1138,dist(x[384],x[562]))) min(dist(x[1087],x[325]),sub(1138,dist(x[1087],x[325]))) min(dist(x[1087],x[596]),sub(1138,dist(x[1087],x[596]))) min(dist(x[83],x[562]),sub(1138,dist(x[83],x[562]))) min(dist(x[83],x[828]),sub(1138,dist(x[83],x[828]))) min(dist(x[659],x[596]),sub(1138,dist(x[659],x[596]))) min(dist(x[758],x[596]),sub(1138,dist(x[758],x[596]))) min(dist(x[622],x[875]),sub(1138,dist(x[622],x[875]))) min(dist(x[622],x[629]),sub(1138,dist(x[622],x[629]))) min(dist(x[120],x[280]),sub(1138,dist(x[120],x[280]))) min(dist(x[120],x[888]),sub(1138,dist(x[120],x[888]))) min(dist(x[733],x[541]),sub(1138,dist(x[733],x[541]))) min(dist(x[733],x[1118]),sub(1138,dist(x[733],x[1118]))) min(dist(x[733],x[875]),sub(1138,dist(x[733],x[875]))) min(dist(x[772],x[493]),sub(1138,dist(x[772],x[493]))) min(dist(x[772],x[495]),sub(1138,dist(x[772],x[495]))) min(dist(x[915],x[919]),sub(1138,dist(x[915],x[919]))) min(dist(x[1023],x[340]),sub(1138,dist(x[1023],x[340]))) min(dist(x[739],x[749]),sub(1138,dist(x[739],x[749]))) min(dist(x[739],x[691]),sub(1138,dist(x[739],x[691]))) min(dist(x[739],x[340]),sub(1138,dist(x[739],x[340]))) min(dist(x[618],x[1097]),sub(1138,dist(x[618],x[1097]))) min(dist(x[618],x[514]),sub(1138,dist(x[618],x[514]))) min(dist(x[618],x[1118]),sub(1138,dist(x[618],x[1118]))) min(dist(x[898],x[191]),sub(1138,dist(x[898],x[191]))) min(dist(x[898],x[722]),sub(1138,dist(x[898],x[722]))) min(dist(x[898],x[814]),sub(1138,dist(x[898],x[814]))) min(dist(x[541],x[738]),sub(1138,dist(x[541],x[738]))) min(dist(x[493],x[495]),sub(1138,dist(x[493],x[495]))) min(dist(x[495],x[865]),sub(1138,dist(x[495],x[865]))) min(dist(x[495],x[340]),sub(1138,dist(x[495],x[340]))) min(dist(x[495],x[22]),sub(1138,dist(x[495],x[22]))) min(dist(x[360],x[280]),sub(1138,dist(x[360],x[280]))) min(dist(x[360],x[694]),sub(1138,dist(x[360],x[694]))) min(dist(x[514],x[489]),sub(1138,dist(x[514],x[489]))) min(dist(x[514],x[691]),sub(1138,dist(x[514],x[691]))) min(dist(x[886],x[865]),sub(1138,dist(x[886],x[865]))) min(dist(x[886],x[161]),sub(1138,dist(x[886],x[161]))) min(dist(x[42],x[804]),sub(1138,dist(x[42],x[804]))) min(dist(x[706],x[357]),sub(1138,dist(x[706],x[357]))) min(dist(x[862],x[1005]),sub(1138,dist(x[862],x[1005]))) min(dist(x[862],x[729]),sub(1138,dist(x[862],x[729]))) min(dist(x[862],x[22]),sub(1138,dist(x[862],x[22]))) min(dist(x[804],x[757]),sub(1138,dist(x[804],x[757]))) min(dist(x[804],x[729]),sub(1138,dist(x[804],x[729]))) min(dist(x[107],x[233]),sub(1138,dist(x[107],x[233]))) min(dist(x[691],x[271]),sub(1138,dist(x[691],x[271]))) min(dist(x[691],x[340]),sub(1138,dist(x[691],x[340]))) min(dist(x[691],x[1118]),sub(1138,dist(x[691],x[1118]))) min(dist(x[614],x[929]),sub(1138,dist(x[614],x[929]))) min(dist(x[671],x[271]),sub(1138,dist(x[671],x[271]))) min(dist(x[280],x[446]),sub(1138,dist(x[280],x[446]))) min(dist(x[280],x[231]),sub(1138,dist(x[280],x[231]))) min(dist(x[280],x[993]),sub(1138,dist(x[280],x[993]))) min(dist(x[158],x[694]),sub(1138,dist(x[158],x[694]))) min(dist(x[302],x[162]),sub(1138,dist(x[302],x[162]))) min(dist(x[340],x[888]),sub(1138,dist(x[340],x[888]))) min(dist(x[340],x[473]),sub(1138,dist(x[340],x[473]))) min(dist(x[888],x[101]),sub(1138,dist(x[888],x[101]))) min(dist(x[888],x[615]),sub(1138,dist(x[888],x[615]))) min(dist(x[101],x[1119]),sub(1138,dist(x[101],x[1119]))) min(dist(x[191],x[233]),sub(1138,dist(x[191],x[233]))) min(dist(x[191],x[919]),sub(1138,dist(x[191],x[919]))) min(dist(x[191],x[1118]),sub(1138,dist(x[191],x[1118]))) min(dist(x[191],x[539]),sub(1138,dist(x[191],x[539]))) min(dist(x[191],x[875]),sub(1138,dist(x[191],x[875]))) min(dist(x[757],x[473]),sub(1138,dist(x[757],x[473]))) min(dist(x[757],x[201]),sub(1138,dist(x[757],x[201]))) min(dist(x[919],x[370]),sub(1138,dist(x[919],x[370]))) min(dist(x[1118],x[1105]),sub(1138,dist(x[1118],x[1105]))) min(dist(x[1118],x[875]),sub(1138,dist(x[1118],x[875]))) min(dist(x[1105],x[41]),sub(1138,dist(x[1105],x[41]))) min(dist(x[1105],x[875]),sub(1138,dist(x[1105],x[875]))) min(dist(x[473],x[413]),sub(1138,dist(x[473],x[413]))) min(dist(x[645],x[535]),sub(1138,dist(x[645],x[535]))) min(dist(x[539],x[415]),sub(1138,dist(x[539],x[415]))) min(dist(x[539],x[1096]),sub(1138,dist(x[539],x[1096]))) min(dist(x[446],x[207]),sub(1138,dist(x[446],x[207]))) min(dist(x[722],x[875]),sub(1138,dist(x[722],x[875]))) min(dist(x[722],x[793]),sub(1138,dist(x[722],x[793]))) min(dist(x[1119],x[538]),sub(1138,dist(x[1119],x[538]))) min(dist(x[327],x[538]),sub(1138,dist(x[327],x[538]))) min(dist(x[320],x[22]),sub(1138,dist(x[320],x[22]))) min(dist(x[45],x[247]),sub(1138,dist(x[45],x[247]))) min(dist(x[1051],x[1068]),sub(1138,dist(x[1051],x[1068]))) min(dist(x[206],x[5]),sub(1138,dist(x[206],x[5]))) min(dist(x[206],x[283]),sub(1138,dist(x[206],x[283]))) min(dist(x[206],x[857]),sub(1138,dist(x[206],x[857]))) min(dist(x[206],x[769]),sub(1138,dist(x[206],x[769]))) min(dist(x[206],x[791]),sub(1138,dist(x[206],x[791]))) min(dist(x[734],x[338]),sub(1138,dist(x[734],x[338]))) min(dist(x[734],x[283]),sub(1138,dist(x[734],x[283]))) min(dist(x[734],x[1094]),sub(1138,dist(x[734],x[1094]))) min(dist(x[338],x[1068]),sub(1138,dist(x[338],x[1068]))) min(dist(x[338],x[1036]),sub(1138,dist(x[338],x[1036]))) min(dist(x[338],x[959]),sub(1138,dist(x[338],x[959]))) min(dist(x[5],x[407]),sub(1138,dist(x[5],x[407]))) min(dist(x[799],x[283]),sub(1138,dist(x[799],x[283]))) min(dist(x[538],x[699]),sub(1138,dist(x[538],x[699]))) min(dist(x[857],x[769]),sub(1138,dist(x[857],x[769]))) min(dist(x[857],x[920]),sub(1138,dist(x[857],x[920]))) min(dist(x[857],x[409]),sub(1138,dist(x[857],x[409]))) min(dist(x[407],x[409]),sub(1138,dist(x[407],x[409]))) min(dist(x[247],x[598]),sub(1138,dist(x[247],x[598]))) min(dist(x[247],x[993]),sub(1138,dist(x[247],x[993]))) min(dist(x[247],x[581]),sub(1138,dist(x[247],x[581]))) min(dist(x[598],x[1030]),sub(1138,dist(x[598],x[1030]))) min(dist(x[993],x[137]),sub(1138,dist(x[993],x[137]))) min(dist(x[1068],x[581]),sub(1138,dist(x[1068],x[581]))) min(dist(x[1068],x[1036]),sub(1138,dist(x[1068],x[1036]))) min(dist(x[1030],x[1053]),sub(1138,dist(x[1030],x[1053]))) min(dist(x[1036],x[322]),sub(1138,dist(x[1036],x[322]))) min(dist(x[1053],x[137]),sub(1138,dist(x[1053],x[137]))) min(dist(x[913],x[68]),sub(1138,dist(x[913],x[68]))) min(dist(x[67],x[909]),sub(1138,dist(x[67],x[909]))) min(dist(x[67],x[1128]),sub(1138,dist(x[67],x[1128]))) min(dist(x[67],x[186]),sub(1138,dist(x[67],x[186]))) min(dist(x[237],x[1128]),sub(1138,dist(x[237],x[1128]))) min(dist(x[536],x[68]),sub(1138,dist(x[536],x[68]))) min(dist(x[371],x[595]),sub(1138,dist(x[371],x[595]))) min(dist(x[371],x[312]),sub(1138,dist(x[371],x[312]))) min(dist(x[371],x[272]),sub(1138,dist(x[371],x[272]))) min(dist(x[68],x[634]),sub(1138,dist(x[68],x[634]))) min(dist(x[254],x[357]),sub(1138,dist(x[254],x[357]))) min(dist(x[254],x[1128]),sub(1138,dist(x[254],x[1128]))) min(dist(x[357],x[994]),sub(1138,dist(x[357],x[994]))) min(dist(x[200],x[163]),sub(1138,dist(x[200],x[163]))) min(dist(x[200],x[321]),sub(1138,dist(x[200],x[321]))) min(dist(x[1128],x[721]),sub(1138,dist(x[1128],x[721]))) min(dist(x[162],x[1122]),sub(1138,dist(x[162],x[1122]))) min(dist(x[163],x[330]),sub(1138,dist(x[163],x[330]))) min(dist(x[321],x[410]),sub(1138,dist(x[321],x[410]))) min(dist(x[321],x[272]),sub(1138,dist(x[321],x[272]))) min(dist(x[827],x[410]),sub(1138,dist(x[827],x[410]))) min(dist(x[410],x[272]),sub(1138,dist(x[410],x[272]))) min(dist(x[1048],x[1041]),sub(1138,dist(x[1048],x[1041]))) min(dist(x[356],x[378]),sub(1138,dist(x[356],x[378]))) min(dist(x[38],x[708]),sub(1138,dist(x[38],x[708]))) min(dist(x[114],x[1091]),sub(1138,dist(x[114],x[1091]))) min(dist(x[467],x[753]),sub(1138,dist(x[467],x[753]))) min(dist(x[467],x[390]),sub(1138,dist(x[467],x[390]))) min(dist(x[467],x[1011]),sub(1138,dist(x[467],x[1011]))) min(dist(x[467],x[894]),sub(1138,dist(x[467],x[894]))) min(dist(x[467],x[503]),sub(1138,dist(x[467],x[503]))) min(dist(x[467],x[378]),sub(1138,dist(x[467],x[378]))) min(dist(x[664],x[516]),sub(1138,dist(x[664],x[516]))) min(dist(x[777],x[741]),sub(1138,dist(x[777],x[741]))) min(dist(x[777],x[179]),sub(1138,dist(x[777],x[179]))) min(dist(x[777],x[1011]),sub(1138,dist(x[777],x[1011]))) min(dist(x[777],x[894]),sub(1138,dist(x[777],x[894]))) min(dist(x[777],x[566]),sub(1138,dist(x[777],x[566]))) min(dist(x[777],x[829]),sub(1138,dist(x[777],x[829]))) min(dist(x[800],x[829]),sub(1138,dist(x[800],x[829]))) min(dist(x[95],x[829]),sub(1138,dist(x[95],x[829]))) min(dist(x[390],x[516]),sub(1138,dist(x[390],x[516]))) min(dist(x[390],x[815]),sub(1138,dist(x[390],x[815]))) min(dist(x[390],x[503]),sub(1138,dist(x[390],x[503]))) min(dist(x[390],x[572]),sub(1138,dist(x[390],x[572]))) min(dist(x[390],x[949]),sub(1138,dist(x[390],x[949]))) min(dist(x[390],x[1091]),sub(1138,dist(x[390],x[1091]))) min(dist(x[873],x[1091]),sub(1138,dist(x[873],x[1091]))) min(dist(x[375],x[815]),sub(1138,dist(x[375],x[815]))) min(dist(x[420],x[940]),sub(1138,dist(x[420],x[940]))) min(dist(x[420],x[643]),sub(1138,dist(x[420],x[643]))) min(dist(x[882],x[815]),sub(1138,dist(x[882],x[815]))) min(dist(x[1011],x[851]),sub(1138,dist(x[1011],x[851]))) min(dist(x[303],x[894]),sub(1138,dist(x[303],x[894]))) min(dist(x[516],x[940]),sub(1138,dist(x[516],x[940]))) min(dist(x[516],x[148]),sub(1138,dist(x[516],x[148]))) min(dist(x[516],x[1041]),sub(1138,dist(x[516],x[1041]))) min(dist(x[940],x[643]),sub(1138,dist(x[940],x[643]))) min(dist(x[148],x[926]),sub(1138,dist(x[148],x[926]))) min(dist(x[783],x[1041]),sub(1138,dist(x[783],x[1041]))) min(dist(x[1041],x[926]),sub(1138,dist(x[1041],x[926]))) min(dist(x[1041],x[378]),sub(1138,dist(x[1041],x[378]))) min(dist(x[503],x[1072]),sub(1138,dist(x[503],x[1072]))) min(dist(x[708],x[643]),sub(1138,dist(x[708],x[643]))) min(dist(x[708],x[1137]),sub(1138,dist(x[708],x[1137]))) min(dist(x[378],x[1137]),sub(1138,dist(x[378],x[1137]))) min(dist(x[770],x[850]),sub(1138,dist(x[770],x[850]))) min(dist(x[463],x[850]),sub(1138,dist(x[463],x[850]))) min(dist(x[463],x[642]),sub(1138,dist(x[463],x[642]))) min(dist(x[61],x[33]),sub(1138,dist(x[61],x[33]))) min(dist(x[1101],x[604]),sub(1138,dist(x[1101],x[604]))) min(dist(x[498],x[355]),sub(1138,dist(x[498],x[355]))) min(dist(x[850],x[935]),sub(1138,dist(x[850],x[935]))) min(dist(x[850],x[681]),sub(1138,dist(x[850],x[681]))) min(dist(x[935],x[707]),sub(1138,dist(x[935],x[707]))) min(dist(x[334],x[707]),sub(1138,dist(x[334],x[707]))) min(dist(x[334],x[604]),sub(1138,dist(x[334],x[604]))) min(dist(x[543],x[443]),sub(1138,dist(x[543],x[443]))) min(dist(x[159],x[289]),sub(1138,dist(x[159],x[289]))) min(dist(x[159],x[923]),sub(1138,dist(x[159],x[923]))) min(dist(x[255],x[761]),sub(1138,dist(x[255],x[761]))) min(dist(x[632],x[354]),sub(1138,dist(x[632],x[354]))) min(dist(x[632],x[891]),sub(1138,dist(x[632],x[891]))) min(dist(x[17],x[843]),sub(1138,dist(x[17],x[843]))) min(dist(x[17],x[43]),sub(1138,dist(x[17],x[43]))) min(dist(x[128],x[134]),sub(1138,dist(x[128],x[134]))) min(dist(x[189],x[256]),sub(1138,dist(x[189],x[256]))) min(dist(x[134],x[818]),sub(1138,dist(x[134],x[818]))) min(dist(x[134],x[383]),sub(1138,dist(x[134],x[383]))) min(dist(x[818],x[178]),sub(1138,dist(x[818],x[178]))) min(dist(x[1084],x[843]),sub(1138,dist(x[1084],x[843]))) min(dist(x[1084],x[1055]),sub(1138,dist(x[1084],x[1055]))) min(dist(x[256],x[73]),sub(1138,dist(x[256],x[73]))) min(dist(x[289],x[354]),sub(1138,dist(x[289],x[354]))) min(dist(x[59],x[761]),sub(1138,dist(x[59],x[761]))) min(dist(x[761],x[354]),sub(1138,dist(x[761],x[354]))) min(dist(x[761],x[318]),sub(1138,dist(x[761],x[318]))) min(dist(x[761],x[178]),sub(1138,dist(x[761],x[178]))) min(dist(x[354],x[781]),sub(1138,dist(x[354],x[781]))) min(dist(x[835],x[843]),sub(1138,dist(x[835],x[843]))) min(dist(x[843],x[392]),sub(1138,dist(x[843],x[392]))) min(dist(x[843],x[43]),sub(1138,dist(x[843],x[43]))) min(dist(x[843],x[73]),sub(1138,dist(x[843],x[73]))) min(dist(x[843],x[331]),sub(1138,dist(x[843],x[331]))) min(dist(x[392],x[597]),sub(1138,dist(x[392],x[597]))) min(dist(x[392],x[923]),sub(1138,dist(x[392],x[923]))) min(dist(x[525],x[1104]),sub(1138,dist(x[525],x[1104]))) min(dist(x[987],x[891]),sub(1138,dist(x[987],x[891]))) min(dist(x[945],x[625]),sub(1138,dist(x[945],x[625]))) min(dist(x[945],x[627]),sub(1138,dist(x[945],x[627]))) min(dist(x[1027],x[1121]),sub(1138,dist(x[1027],x[1121]))) min(dist(x[1121],x[683]),sub(1138,dist(x[1121],x[683]))) min(dist(x[1121],x[1082]),sub(1138,dist(x[1121],x[1082]))) min(dist(x[683],x[1028]),sub(1138,dist(x[683],x[1028]))) min(dist(x[331],x[890]),sub(1138,dist(x[331],x[890]))) min(dist(x[331],x[1003]),sub(1138,dist(x[331],x[1003]))) min(dist(x[331],x[975]),sub(1138,dist(x[331],x[975]))) min(dist(x[331],x[1055]),sub(1138,dist(x[331],x[1055]))) min(dist(x[890],x[449]),sub(1138,dist(x[890],x[449]))) min(dist(x[890],x[735]),sub(1138,dist(x[890],x[735]))) min(dist(x[890],x[627]),sub(1138,dist(x[890],x[627]))) min(dist(x[747],x[1003]),sub(1138,dist(x[747],x[1003]))) min(dist(x[1028],x[796]),sub(1138,dist(x[1028],x[796]))) min(dist(x[1003],x[763]),sub(1138,dist(x[1003],x[763]))) min(dist(x[763],x[75]),sub(1138,dist(x[763],x[75]))) min(dist(x[1006],x[627]),sub(1138,dist(x[1006],x[627]))) min(dist(x[711],x[176]),sub(1138,dist(x[711],x[176]))) min(dist(x[711],x[997]),sub(1138,dist(x[711],x[997]))) min(dist(x[625],x[939]),sub(1138,dist(x[625],x[939]))) min(dist(x[1129],x[693]),sub(1138,dist(x[1129],x[693]))) min(dist(x[914],x[997]),sub(1138,dist(x[914],x[997]))) min(dist(x[693],x[78]),sub(1138,dist(x[693],x[78]))) min(dist(x[693],x[1134]),sub(1138,dist(x[693],x[1134]))) min(dist(x[1104],x[75]),sub(1138,dist(x[1104],x[75]))) min(dist(x[665],x[304]),sub(1138,dist(x[665],x[304]))) min(dist(x[559],x[655]),sub(1138,dist(x[559],x[655]))) min(dist(x[161],x[655]),sub(1138,dist(x[161],x[655]))) min(dist(x[113],x[304]),sub(1138,dist(x[113],x[304]))) </minimize>
  </objectives>
</instance>
